Workbook

Sheet Fondo de reservas
B3: CONDOMINIO EL FRAMBOYANT
B4: Calle 30 de Marzo, Las Terrenas, Samaná, República Dominicana 32200
G6: Periodo de 01/01 hasta 31/12/2024
C7: FONDO DE RESERVAS
C9: Descripción | D9: Fecha | E9: Tipo | F9: Debito | G9: Credito
C10: Saldo balance al 31/12/2023 | D10: 45292 | E10: BQ | G10: 80530.98
C11: Retiro-Compensacion deuda A1 | D11: 45467 | E11: BQ | F11: -24574
C12: Retiro- Compra bomba sumergible | D12: 45654 | E12: BQ | F12: -36205.11
E123: TOTAL | F123: =SUBTOTAL(109,F10:F122) -> -60779.11 | G123: =SUBTOTAL(109,G10:G122) -> 80530.98
C125: TOTAL DÉBITO | F125: =F123 -> -60779.11
C126: TOTAL CRÉDITO | G126: =G123 -> 80530.98
C127: BALANCE AL DÍA | G127: =G126+F125 -> 19751.87

Sheet Caja Chica-Cta.Bco
A3: CONDOMINIO EL FRAMBOYANT | H3: CONDOMINIO EL FRAMBOYANT
A4: Calle 30 de Marzo, Las Terrenas, Samaná, República Dominicana 32200 | H4: Calle 30 de Marzo, Las Terrenas, Samaná, República Dominicana 32200
F6: Periodo de 01/01 hasta 31/12/2024 | M6: Periodo de 01/01 hasta 31/12/2024
B7: Estado CAJA CHICA | I7: Estado Cuenta Bancaria/ Banco Popular
B9: Descripción | C9: Fecha | D9: Tipo | E9: Debito | F9: Credito | I9: Descripción | J9: Fecha | K9: Tipo | L9: Debito | M9: Credito
B10: Saldo balance al 31/12/2023 | C10: 45292 | D10: CA | F10: 38550.46 | I10: Saldo balance al 31/12/2023 | J10: 45292 | K10: BQ | M10: 284157.42
B11: Honorario Administrador Enero 2024 | C11: 45293 | D11: CA | E11: -15000 | I11: Luz y Fuerza Diciembre 2023 | J11: 45296 | K11: BQ | L11: -523.82
B12: INAPA Enero 2024 | C12: 45303 | D12: CA | E12: -3600 | I12: 1 camión del agua – El Flaco | J12: 45296 | K12: BQ | L12: -1500
B13: 2 pastillas de cloro para registro agua pluvial | C13: 45303 | D13: CA | E13: -100 | I13: Impuesto 0.15% DGII | J13: 45296 | K13: BQ | L13: -2.25
B14: Registro acta AGE 12/01 ayuntamiento LT | C14: 45310 | D14: CA | E14: -200 | I14: Rep. cambio de luce spot defectuoso-Crismar | J14: 45302 | K14: BQ | L14: -2140
B15: Recogida basura Enero 2024 | C15: 45322 | D15: CA | E15: -1000 | I15: Impuesto 0.15% DGII | J15: 45302 | K15: BQ | L15: -3.21
B16: Honorario Administrador Febrero 2024 | C16: 45323 | D16: CA | E16: -15000 | I16: Materiales plomería y multa demora A7 – Wilner | J16: 45310 | K16: BQ | L16: -6538.23
B17: Honorario del Alguacil para notificación a A-1 | C17: 45330 | D17: CA | E17: -4000 | I17: Impuesto 0.15% DGII | J17: 45310 | K17: BQ | L17: -9.81
B18: Honorario Administrador para AGE 12-01-2024 | C18: 45331 | D18: CA | E18: -2500 | I18: Interés | J18: 45322 | K18: BQ | M18: 60.02
B19: Reembolso a Jeffrey cargo DGII transf banco – A1 | C19: 45331 | D19: CA | E19: -72.56 | I19: Impuesto | J19: 45322 | K19: BQ | L19: -6
B20: Entrada a caja chica desde cuenta banco | C20: 45334 | D20: CA | F20: 20000 | I20: Pago GUERIN-A1 (47 720,90+72,56) | J20: 45331 | K20: BQ | M20: 47793.46
B21: Pago ENGEL – A5 | C21: 45336 | D21: CA | F21: 15000 | I21: Luz y Fuerza Enero 2024 | J21: 45331 | K21: BQ | L21: -710.7
B22: 2 camiones de séptico | C22: 45337 | D22: CA | E22: -14000 | I22: Retiro para caja chica | J22: 45334 | K22: BQ | L22: -20000
B23: Pago FACQUET – A4 | C23: 45342 | D23: CA | F23: 12230 | I23: Pago ONDELLA – A3 | J23: 45335 | K23: BQ | M23: 24134
B24: Registro acta AGO 13/02 ayuntamiento LT | C24: 45342 | D24: CA | E24: -200 | I24: Pago SANTOS – A6 | J24: 45334 | K24: BQ | M24: 24787
B25: Pago a Jeffrey cargo MoneyGram/Deposito – A2 | C25: 45342 | D25: CA | E25: -1000 | I25: Pago HAZELTINE – A7 | J25: 45338 | K25: BQ | M25: 44170.7
B26: Reembolso a Jeffrey cargo DGII transf banco – A7 | C26: 45343 | D26: CA | E26: -221.59 | I26: Pago GUERIN – A1 | J26: 45339 | K26: BQ | M26: 35005.6
B27: Devolucion Material NCB0400046722 Obra contadores, Decision AGO 13.02.24 orden 7 | C27: 45348 | D27: CA | F27: 36150.69
B28: Recogida basura Febrero 2024 | C28: 45351 | D28: CA | E28: -1000 | I28: Pago METAYER-JEAN – A2 | J28: 45342 | K28: BQ | M28: 38625
B29: Honorario Administrador Marzo 2024 | C29: 45352 | D29: CA | E29: -15000 | I29: Pago HAZELTINE – A7 (26,803.85 + 5,221.59) | J29: 45343 | K29: BQ | M29: 32025.44
B30: Pago ONDELLA – A3 | C30: 45358 | D30: CA | F30: 17600 | I30: Avance 60% trabajo muro exterior – Edison | J30: 45343 | K30: BQ | L30: -126944.4
B31: Pago ENGEL – A5 | C31: 45358 | D31: CA | F31: 8900 | I31: Impuesto 0.15% DGII | J31: 45343 | K31: BQ | L31: -190.42
B32: Pago FACQUET – A4 | C32: 45359 | D32: CA | F32: 6015 | I32: Avance 60% trabajo área séptico – Edison | J32: 45343 | K32: BQ | L32: -82584
B33: Materiales Desague Pluvial NCB0400046722 | C33: 45364 | D33: CA | E33: -21368.35
B34: Honorario Administrador (oficina inapa 2 veces, agua negra) | C34: 45371 | D34: CA | E34: -2500
B35: Limpieza frente a la calle y plantas creciendo en drenaje | C35: 45371 | D35: CA | E35: -500
B36: Materiales Desague Pluvial NCB0400046722 | C36: 45371 | D36: CA | E36: -1351.01
B37: Recogida basura Marzo 2024 | C37: 45373 | D37: CA | E37: -1000 | I37: Impuesto 0.15% DGII | J37: 45343 | K37: BQ | L37: -123.88
B38: Materiales Desague Pluvial NCB0400046722 | C38: 45373 | D38: CA | E38: -219.64
B39: Materiales Desague Pluvial NCB0400046722 | C39: 45374 | D39: CA | E39: -399.02
B40: Pago Eddy septico adjuste presupuesto AGE 12.01.24 | C40: 45376 | D40: CA | E40: -14000 | I40: Interés | J40: 45351 | K40: BQ | M40: 63.95
B41: Materiales Desague Pluvial NCB0400046722 | C41: 45376 | D41: CA | E41: -1543.05
B42: Honorario administrador, reunion ayuntamiento- aguas negras | C42: 45377 | D42: CA | E42: -2500 | I42: Impuesto | J42: 45351 | K42: BQ | L42: -6.4
B43: Mantenimiento y rep. Trabajos emergencia, A-1 | C43: 45377 | D43: CA | E43: -3000 | I43: Pago SANTOS – A6 | J43: 45358 | K43: BQ | M43: 18230.03
B44: Materiales Desague Pluvial NCB0400046722 | C44: 45378 | D44: CA | E44: -702.99
B45: Pago impuesto 0.15 DGII transferencia de fondos a cuenta popular | C45: 45385 | D45: CA | E45: -314.11 | I45: Luz y Fuerza Febrero 2024 | J45: 45359 | K45: BQ | L45: -912.52
B46: Pago Honorarios Administrador Mes de Abril 2024 | C46: 45385 | D46: CA | E46: -15000 | I46: INAPA Febrero 2024 | J46: 45359 | K46: BQ | L46: -3600
B47: Materiales Desague Pluvial NCB0400046722 | C47: 45394 | D47: CA | E47: -15071.96
B48: Honorario Administrador (Ferreteria-Emergencia- Bomba de agua) | C48: 45396 | E48: -2500 | I48: Impuesto 0.15% DGII | J48: 45359 | K48: BQ | L48: -5.4
B49: Pago ENGEL – A5 | C49: 45404 | D49: CA | F49: 18600 | I49: Materiales Trabajo registro aguas pluviales subterráneos – Crismar | J49: 45363 | K49: BQ | L49: -13261
B50: Recogida 1 camion de Basura | C50: 45404 | D50: CA | E50: -1500 | I50: Impuesto 0.15% DGII | J50: 45363 | K50: BQ | L50: -19.89
B51: Limpieza parqueo principal, caños y bomba de relevaje | C51: 45404 | D51: CA | E51: -2500 | I51: 2do avance 20% trabajo muro exterior – Edison | J51: 45367 | K51: BQ | L51: -42314.8
B52: Compra de carretilla y material | C52: 45404 | D52: CA | E52: -7962.95 | I52: Impuesto 0.15% DGII | J52: 45367 | K52: BQ | L52: -63.47
B53: Pago METAYER-JEAN- A2 | C53: 45408 | D53: CA | F53: 22556.56
B54: Pago a Jeffrey cargo MoneyGram/Deposito – A2 | C54: 45408 | D54: CA | E54: -1000
B55: Pago ONDELLA – A3 | C55: 45412 | D55: CA | F55: 33000 | I55: 2do avance 20% trabajo área séptico – Edison | J55: 45367 | K55: BQ | L55: -27528
B56: Pago Limpieza cisterna | C56: 45412 | D56: CA | E56: -3000 | I56: Impuesto 0.15% DGII | J56: 45367 | K56: BQ | L56: -41.29
B57: Recogida basura Abril 2024 | C57: 45412 | D57: CA | E57: -1000 | I57: INAPA Marzo 2024 | J57: 45367 | K57: BQ | L57: -3600
B58: Eddy-Pago sueldo trabajo area septicos AGE12.01.23 | C58: 45412 | D58: CA | E58: -27528 | I58: Impuesto 0.15% DGII | J58: 45367 | K58: BQ | L58: -5.4
B59: Compra de Codo 32x32 y mano de obra, reparaciones | C59: 45413 | D59: CA | E59: -1772 | I59: MDO Trabajo registro aguas pluviales subterráneos + Rep. Flota agua Inapa – Crismar | J59: 45372 | K59: BQ | L59: -7000
B60: Pago ENGEL – A5 | C60: 45414 | D60: CA | F60: 2000 | I60: Impuesto 0.15% DGII | J60: 45372 | K60: BQ | L60: -10.5
B71: Pago FACQUET – A4 | C71: 45415 | D71: CA | F71: 16750.58 | I71: Pago sueldo 20% pared cerca AGE 27.09.23, punto 12 | J71: 45384 | K71: BQ | L71: -42314.8
B72: Cargo administrador recordatorio pago 15 dias despues venc.Pedido de fondo – cuota extraordinaria Voto electronico del 09-04-2024 $10,082.01 | C72: 45418 | E72: -1000
B73: Manuel Pierre- Adelanto material y MDO obra 2 (voto elec.9.04.24) | C73: 45421 | D73: CA | E73: -45000 | I73: MDO drenaje pluvial+penalidad cancelacion AGO 24, AGE 27.09.23 Orden #10+mantenimiento y reparacion | J73: 45384 | K73: BQ | L73: -23000
B74: Andre Wemni-Arreglo y limpieza area A2 y Jardin A2, luego de construccion septico | C74: 45435 | D74: CA | E74: -5000 | I74: Cargo Mensual TD clasica | J74: 45384 | K74: BQ | L74: -65
B75: Honorario Administrador-Emergencia bomba agua luego de tormenta electrica | C75: 45437 | D75: CA | E75: -2500 | I75: Luz y fuerza marzo 2024 | J75: 45385 | K75: BQ | L75: -1428.3
B76: Pago jardinero + limpieza de escombros | C76: 45439 | D76: CA | E76: -2500 | I76: Pago Inapa Abril-2024 | J76: 45385 | K76: BQ | L76: -3600
B77: Cargo administrador recordatorio pago 15 dias despues venc Cuota diff presupuesto gastos reales 12.01.24 - Orden6) | C77: 45443 | D77: CA | E77: -1000
B78: Entrada a caja chica desde cuenta banco | C78: 45449 | D78: CA | F78: 18773.6 | I78: Compra 1 camion de agua | J78: 45387 | K78: BQ | L78: -1000
B79: Walner Manuel- Adelanto por material, pintura+MDO Voto elec del 15.04.24 | C79: 45450 | D79: CA | E79: -10000 | I79: Impuesto 0.15% DGII | J79: 45387 | K79: BQ | L79: -103.37
B80: Andre Wemni-Material preparacion baden Voto Elec.31.05.24 Presupuesto B2 | C80: 45453 | D80: CA | E80: -3000 | I80: Swich Flota electrica y mano de obra instalacion | J80: 45387 | K80: BQ | L80: -2265
B81: Andre Wemni-Presupuesto obra B-2 voto elec.31.05.24 | C81: 45455 | D81: CA | E81: -3886 | I81: Compra 1 camion de agua | J81: 45394 | K81: BQ | L81: -1000
B82: Entrada a caja chica desde cuenta banco | C82: 45460 | D82: CA | F82: 15000 | I82: Impuesto 0.15% DGII | J82: 45394 | K82: BQ | L82: 1.5
B83: Mano de obra de limpieza Jardineria mensual pared/escalera | C83: 45469 | D83: CA | E83: -2000
B84: Entrada a caja chica desde cuenta banco | C84: 45467 | D84: CA | F84: 10000 | I84: Materiales y Mdo Obra excepcional, bomba sumergible (crismar) | J84: 45394 | K84: BQ | L84: -8550
B85: Mano de obra Manuel Pierre/sueldo obra n2-voto elec 9-04-24 | C85: 45467 | D85: CA | E85: -12000 | I85: Compra 1 camion de agua (averia inapa) | J85: 45397 | K85: BQ | L85: -1000
B86: Adiel Tassaint- limpieza de caños puerta principal | C86: 45469 | D86: CA | E86: -1000 | I86: Honorario supervisor administracion | J86: 45397 | K86: BQ | L86: -32318
B87: Cargo administrador segundo recordatorio pago 45 dias despues venc.A-1 (cuota 09.04.2024) | C87: 45473 | D87: CA | E87: -3000 | I87: Cargo Bancario | J87: 45400 | K87: BQ | L87: -55
B88: Entrada a caja chica desde cuenta banco | C88: 45478 | D88: CA | F88: 10000 | I88: Impuesto 0.15% DGII | J88: 45401 | K88: BQ | L88: -51.48
B89: walner Manuel- Voto elec del 09.04.24 Obra 1- Sueldo | C89: 45478 | D89: CA | E89: -9220 | I89: Compra 1 camion de agua (averia inapa) | J89: 45407 | K89: BQ | L89: -1000
B90: Ferreteria Bonillas- Cambio luz Parqueo A2+MDO | C90: 45481 | D90: CA | E90: =-956-500 -> -1456 | I90: Compra materiales+MDO reparaciones (crismar) | J90: 45407 | K90: BQ | L90: -2775
B91: Honorarios del Alguacil para notificación a A-1 | C91: 45481 | D91: CA | E91: -5000 | I91: Impuesto 0.15% DGII | J91: 45408 | K91: BQ | L91: -5.66
B92: Pago FACQUET – A4 | C92: 45488 | D92: CA | F92: 10600 | I92: Pago HAZELTINE – A7 | J92: 45411 | K92: BQ | M92: 53225.89
B93: Pago ENGEL – A5 | C93: 45488 | D93: CA | F93: 13025 | I93: Pago SANTOS – A6 | J93: 45412 | K93: BQ | M93: 33871.61
B94: Pago METAYER-JEAN- A2 | C94: 45488 | D94: CA | F94: 18000 | I94: Compra 1 camion de agua (averia inapa) | J94: 45412 | K94: BQ | L94: -1000
B95: Crismar Plomero- Material y MDO trabajos plomeria Emergencia desague A5 y Cisterna | C95: 45488 | D95: CA | E95: -12048 | I95: Compra 1 camion de agua (averia inapa) | J95: 45413 | K95: BQ | L95: -1000
B96: Viaje un camion de Septico- Vaciado | C96: 45488 | D96: CA | E96: -7000 | I96: CARGO MENSual TD clasica | J96: 45413 | K96: BQ | L96: -65
B97: Jardin A2 y Palma Jardin A6 | C97: 45489 | D97: CA | E97: -4500 | I97: Impuesto 0.15% DGII | J97: 45415 | K97: BQ | L97: -3
B98: Pago ONDELLA – A3 | C98: 45490 | D98: CA | F98: 20900 | I98: Luz y fuerza Abril 2024 | J98: 45418 | K98: BQ | L98: -949.9
B99: Limpieza Jardin | C99: 45490 | D99: CA | E99: -1000 | I99: INAPA Mayo 2024 | J99: 45418 | K99: BQ | L99: -3600
B100: Roberto Green- Trabajo emergencias desague duchas A7-Problema similar A5 | C100: 45491 | D100: CA | E100: -7500 | I100: Impuesto 0.15% DGII | J100: 45422 | K100: BQ | L100: -5.4
B101: Andre wemni- Trabajo emergencia Septico- zanja y tubos | C101: 45492 | D101: CA | E101: -12298.45 | I101: Impuesto 0.15% DGII | J101: 45433 | K101: BQ | L101: -55
B102: Viaje un camion de Septico- Vaciado | C102: 45492 | D102: CA | E102: -7000
B103: Chavan Mesamours - Trabajo emerencia Septico - Plomeria, bomba y electricidad | C103: 45492 | D103: CA | E103: -18369.23
B104: Llave ajustable parilla porton | C104: 45499 | D104: CA | E104: -350.98 | I104: Compra 1 camion de agua (averia inapa) | J104: 45437 | K104: BQ | L104: -1000
B105: Limpieza aceras y parillas frente al residencial | C105: 45502 | D105: CA | E105: -1000 | I105: Honorarios 10% supervision trabajos AGE ene 24 septicos+ registro agua pluvia | J105: 45439 | K105: BQ | L105: -16931.4
I106: Honorarios Administrador-Digitalizacion del reglamento condominio | J106: 45440 | K106: BQ | L106: -8000
B107: Entrada a caja chica desde cuenta banco | C107: 45511 | D107: CA | F107: 20000 | I107: Impuesto 0.15% DGII | J107: 45443 | K107: BQ | L107: -1.5
B108: Entrada a caja chica desde cuenta banco | C108: 45513 | D108: CA | F108: 14000 | I108: Cargo Mensual TD clasica | J108: 45446 | K108: BQ | L108: -65
B109: Honorarios Administrador- JULIO | C109: 45513 | D109: CA | E109: -15000 | I109: Pago Honorarios Administrador Mes de Mayo 2024 | J109: 45449 | K109: BQ | L109: -15000
B110: Crismar Plomero- Trabajo emergencia-Limpieza bomba pequeña y MDO filtro bomba cisterna | C110: 45513 | D110: CA | E110: -7500 | I110: Retiro para caja chica | J110: 45449 | K110: BQ | L110: -18773.6
B111: Pago ENGEL – A5 | C111: 45527 | D111: CA | F111: 7000 | I111: Recogida de Basura Mayo 2024 | J111: 45455 | K111: BQ | L111: -1000
B112: Pago METAYER-JEAN- A2 | C112: 45531 | D112: CA | F112: 12400 | I112: INAPA Junio 2024 | J112: 45455 | K112: BQ | L112: -3600
B113: Jardinero- Limpieza Mensual | C113: 45532 | D113: CA | E113: -2000 | I113: Luz y fuerza Mayo 2024 | J113: 45455 | K113: BQ | L113: -748.07
B114: Pago ONDELLA – A3 | C114: 45534 | D114: CA | F114: 11100 | I114: Impuesto 0.15% DGII | J114: 45457 | K114: BQ | L114: -6.9
...

Sheet Gastos detallados
A3: CONDOMINIO EL FRAMBOYANT
A4: Calle 30 de Marzo, Las Terrenas, Samaná, República Dominicana 32200
E6: Periodo de 01/01 hasta 31/12/2024
B7: Estado detallados de gastos
B9: INAPA (Contrato 321528) / Agua | C9: Fecha | D9: Monto
B10: 1 Camión de agua (interrupción servicio por averías) | C10: 45296 | D10: 1500
B11: INAPA Enero 2024 | C11: 45303 | D11: 3600
B12: INAPA Febrero 2024 | C12: 45359 | D12: 3600
B13: INAPA Marzo 2024 | C13: 45367 | D13: 3600
B14: INAPA Abril 2024 | C14: 45385 | D14: 3600
B15: 1 Camion de Agua | C15: 45387 | D15: 1000
B16: 1 Camión de agua (interrupción servicio por averías) | C16: 45394 | D16: 1000
B17: 1 Camión de agua (interrupción servicio por averías) | C17: 45397 | D17: 1000
B18: 1 Camión de agua (interrupción servicio por averías) | C18: 45407 | D18: 1000
B19: 1 Camión de agua (interrupción servicio por averías) | C19: 45412 | D19: 1000
B20: 1 Camión de agua (interrupción servicio por averías) | C20: 45413 | D20: 1000
B21: INAPA MAYO 2024 | C21: 45418 | D21: 3600
... B36: INAPA Noviembre 2024 | C36: 45626 | D36: 3600
B37: Total | D37: =SUM(D10:D36) -> 67100
B39: LUZ Y FUERZA / Electricidad | C39: Fecha | D39: Monto
B40: Luz Diciembre 2023 (55 kwh) | C40: 45296 | D40: 523.82
B41: Luz Enero 2024 (80 kwh) | C41: 45331 | D41: 710.7
B42: Luz Febrero 2024 (107 kwh) | C42: 45359 | D42: 912.52
B43: Luz Marzo 2024 (176 kwh) | C43: 45385 | D43: 1428.3
B44: Luz Abril 2024 (112 kwh) | C44: 45418 | D44: 949.9
B45: Luz y Mayo 2024 (85 khw) | C45: 45455 | D45: 748.07
B46: Luz y Junio 2024 (71khw) | C46: 45504 | D46: 643.42
B47: Luz Julio 2024 (92kh) | C47: 45531 | D47: 800.4
B48: Luz Agosto 2024 (97khw) | C48: 45552 | D48: 837.77
B49: Luz Septiembre 2024 (71khw) | C49: 45593 | D49: 643.42
B50: Luz Octubre 2024 (64khw) | C50: 45623 | D50: 591.1
B51: Luz Noviembre 2024 (105khw) | C51: 45638 | D51: 897.57
B52: Total | D52: =SUM(D40:D51) -> 9686.99
B54: Cargos Bancario / Banco Popular | C54: Fecha | D54: Monto
B55: Impuesto 0.15% DGII | C55: 45296 | D55: 2.25
B56: Impuesto 0.15% DGII | C56: 45302 | D56: 3.21
B57: Impuesto 0.15% DGII | C57: 45310 | D57: 9.81
B58: Interés | C58: 45322 | D58: -60.02
B59: Impuesto | C59: 45322 | D59: 6
B60: Impuesto 0.15% DGII | C60: 45343 | D60: 190.42
B61: Impuesto 0.15% DGII | C61: 45343 | D61: 123.88
B62: Interés | C62: 45351 | D62: -63.95
B63: Impuesto | C63: 45351 | D63: 6.4
B64: Impuesto 0.15% DGII | C64: 45359 | D64: 5.4
B65: Impuesto 0.15% DGII | C65: 45363 | D65: 19.89
B66: Impuesto 0.15% DGII | C66: 45367 | D66: 63.47
... B104: Impuesto 0.15% DGII | C104: 45618 | D104: 67.4
B106: Total | D106: =SUM(D55:D104) -> 1985.87
B108: Reparaciones / Mantenimientos | C108: Fecha | D108: Monto
B109: 2 pastillas de cloro para registro agua pluvial | C109: 45303 | D109: 100
B110: Rep. cambio de luce spot defectuoso-Crismar | C110: 45302 | D110: 2140
B111: 2 camiones de séptico | C111: 45337 | D111: 14000
B112: Reparación flota agua Inapa + Mant. Tanque de presión – Crismar | C112: 45372 | D112: 1000
B113: Limpieza frente a la calle y plantas creciendo en drenaje | C113: 45371 | D113: 500
B114: Mantenimiento y rep. Trabajos emergencia, A-1 | C114: 45377 | D114: 3000
B115: Swich flota electrica y mano de obra | C115: 45387 | D115: 2265
B116: Obra excepcional bomba sumergible (crismar) | C116: 45394 | D116: 8550
B117: Limpieza parqueo principal, caños y bomba de relevaje | C117: 45404 | D117: 2500
B118: Compra de carretilla y material | C118: 45404 | D118: 7962.95
B119: Compra materiales+MDO reparaciones (crismar) | C119: 45407 | D119: 2775
B120: Pago Limpieza cisterna | C120: 45412 | D120: 3000
... B156: Adiel Toussait- Limpieza parqueo y parillas | C156: 45623 | D156: 2000
B157: Total | D157: =SUM(D109:D156) -> 143594.93
B159: Seguro Incendio y R.C. | C159: Fecha | D159: Monto
B160: Seguro Incendio + RC (Universal)
B161: Total | D161: =SUM(D160) -> 0
B163: Basura / Recogida mensual | C163: Fecha | D163: Monto
B164: Recogida basura Enero 2024 | C164: 45322 | D164: 1000
B165: Recogida basura Febrero 2024 | C165: 45351 | D165: 1000
B166: Recogida basura Marzo 2024 | C166: 45373 | D166: 1000
B167: Recogida 1 camion de Basura | C167: 45404 | D167: 1500
B168: Recogida basura Abril 2024 | C168: 45412 | D168: 1000
B169: Recogida basura Mayo 2024 | C169: 45455 | D169: 1000
B170: Recogida basura Junio 2024 | C170: 45474 | D170: 1000
B171: Recogida basura Julio 2024 | C171: 45504 | D171: 1000
B172: Recogida basura Agosto 2024 | C172: 45531 | D172: 1000
B173: Recogida basura Septiembre 2024 | C173: 45552 | D173: 1000
B174: Recogida basura Octubre 2024 | C174: 45593 | D174: 1000
B175: Recogida basura Noviembre 2024 | C175: 45595 | D175: 1000
B176: Total | D176: =SUM(D164:D175) -> 12500
B178: Honorarios del Administrador | C178: Fecha | D178: Monto
B179: Honorario Administrador Enero 2024 | C179: 45293 | D179: 15000
B180: Honorario Administrador Febrero 2024 | C180: 45323 | D180: 15000
B181: Honorario Administrador Marzo 2024 | C181: 45352 | D181: 15000
B182: Honorario Administrador Abril 2024 | C182: 45385 | D182: 15000
B183: Honorario supervisor (administracion) | C183: 45397 | D183: 32318
B184: Honorario Administrador Mayo 2024 | C184: 45449 | D184: 15000
B185: Honorarios Administrador JUNIO 2024 | C185: 45485 | D185: 15000
B186: Honorarios Administrador- JULIO | C186: 45513 | D186: 15000
B187: Honorarios Administrador- AGOSTO | C187: 45540 | D187: 15000
B188: Honorarios Administrador- Septiembre | C188: 45565 | D188: 15000
B189: Honorarios Administrador Octubre 2024 | C189: 45601 | D189: 15000
B190: Honorarios Administrador Noviembre 2024 | C190: 45623 | D190: 15000
B191: Total | D191: =SUM(D179:D190) -> 197318
B193: Honorarios del Administrador (Extras) | C193: Fecha | D193: Monto
B194: Honorario Administrador para AGE 12-01-2024 | C194: 45331 | D194: 2500
B195: Honorario Administrador (oficina inapa 2 veces, agua negra) | C195: 45371 | D195: 2500
B196: Honorario administrador, reunion ayuntamiento- aguas negras | C196: 45377 | D196: 2500
B197: Honorario Administrador (Ferreteria-Emergencia) | C197: 45396 | D197: 2500
B198: Honorario Administrador (Emergencia-bomba agua) | C198: 45437 | D198: 2500
...

Sheet PedidoAGE12-01
A3: CONDOMINIO EL FRAMBOYANT
A4: Calle 30 de Marzo, Las Terrenas, Samaná, República Dominicana 32200
F6: Cuota Extraordinaria del 2024
B7: Pedido de fondo para Trabajos decidido en AGE 12/01/2024
E9: Total
B11: Trabajo elevación de nivel área de los sépticos | E11: 124000
B12: Asamblea General Extraordinaria punto 4 (aprobado unanimidad)
B13: Voto electrónico realizado durante 19/01 - 24/01/2024 (100% de emitidos : A2/A3/A6/A7)
B15: Trabajo registro de aguas pluviales subterráneos | E15: 17647.18
B16: Asamblea General Extraordinaria punto 5 (aprobado unanimidad)
B17: Voto electrónico realizado durante 19/01 - 24/01/2024 (100% de emitidos : A2/A3/A6/A7)
B19: *Honorarios 10% para seguimientos y supervisores de trabajos | E19: =(E11+E15)*0.1 -> 14164.718
D21: Monto total | E21: =SUM(E10:E20) -> 155811.9
B22: Notas;
B23: Esta cuota extraordinaria es la manera provisional (presupuestos).
B24: La cierre contable del ejercicio 2024 concluirá una vez que se apruebe en la Asamblea General
B25: Ordinaria del principio 2025.
B27: Les pedimos de realizar su pago lo antes posible.
B28: Les recordamos que tiene 15 días de pagar, en contrario 2% de mora será aplicado.
B30: Repartición de Cuota Extraordianaria AGE 12-01-2024 | E30: =E21 -> 155811.9 | H30: Unidad | I30: Total monto | J30: Valor RD$ | K30: Total valor RD$ | L30: Repartición % | M30: Monto/cada
B31: Propietario | C31: UNIDAD | D31: % | E31: Monto a pagar | H31: 1 | I31: =E30 -> 155811.9 | J31: 3386200 | K31: 26236200 | L31: =(J31/J38)*100 -> 12.906595 | M31: =(I31*J31/K31) -> 20110.01 | N31: 20110.01
B32: Serge GUERRIN | C32: A-1 | D32: 0.1291 | E32: 20110.01 | H32: 2 | I32: =E30 -> 155811.9 | J32: 3453400 | K32: 26236200 | L32: =(J32/J38)*100 -> 13.162729 | M32: =(I32*J32/K32) -> 20509.098 | N32: 20509.1
B33: Hervé METAYER | C33: A-2 | D33: 0.1316 | E33: 20509.1 | H33: 3 | I33: =E30 -> 155811.9 | J33: 4063600 | K33: 26236200 | L33: =(J33/J38)*100 -> 15.488523 | M33: =(I33*J33/K33) -> 24132.962 | N33: 24132.96
B34: Frédéric ONDELLA | C34: A-3 | D34: 0.1549 | E34: 24132.96 | H34: 4 | I34: =E30 -> 155811.9 | J34: 2061000 | K34: 26236200 | L34: =(J34/J38)*100 -> 7.8555584 | M34: =(I34*J34/K34) -> 12239.895 | N34: 12239.9
B35: Patricia FACQUET | C35: A-4 | D35: 0.0786 | E35: 12239.9 | H35: 5 | I35: =E30 -> 155811.9 | J35: 2540000 | K35: 26236200 | L35: =(J35/J38)*100 -> 9.6812801 | M35: =(I35*J35/K35) -> 15084.586 | N35: 15084.59
B36: Gernot ENGER | C36: A-5 | D36: 0.0968 | E36: 15084.59 | H36: 6 | I36: =E30 -> 155811.9 | J36: 4173600 | K36: 26236200 | L36: =(J36/J38)*100 -> 15.907792 | M36: =(I36*J36/K36) -> 24786.232 | N36: 24786.23
B37: Inversiones Ter 187 eirl (Karina SANTOS) | C37: A-6 | D37: 0.1591 | E37: 24786.23 | H37: 7 | I37: =E30 -> 155811.9 | J37: 6558400 | K37: 26236200 | L37: =(J37/J38)*100 -> 24.997523 | M37: =(I37*J37/K37) -> 38949.114 | N37: 38949.11
B38: Jonathan HAZELTINE | C38: A-7 | D38: 0.25 | E38: 38949.11 | J38: =SUM(J31:J37) -> 26236200 | L38: =SUM(L31:L37) -> 100 | M38: =SUM(M31:M37) -> 155811.9 | N38: =SUM(N31:N37) -> 155811.9
B39: Total | D39: =SUM(D32:D38) -> 1.0001 | E39: =SUM(E32:E38) -> 155811.9

Sheet PedidoVotoElec-09-04
A3: CONDOMINIO EL FRAMBOYANT
A4: Calle 30 de Marzo, Las Terrenas, Samaná, República Dominicana 32200
F6: Cuota Extraordinaria del 2024
B7: Pedido de fondo para Trabajos decidido en Voto electronico Del 09-04-2024
E9: Total
B10: Obra 1:
B11: Trabajo Pintura pared cerca entre el terreno al Norte y A-3-Parqueo A3 ambos lados | E11: 19220
B13: *Honorarios 10% para seguimientos y supervisores de trabajos | E13: =E11*0.1 -> 1922
B15: Obra 2:
B16: Dos parillas de metal para el pasaje porton principal y entrada A2-A3 | E16: 57000
D21: Monto total | E21: =SUM(E10:E20) -> 78142
B22: Notas;
B23: Esta cuota extraordinaria es la manera provisional (presupuestos).
B24: La cierre contable del ejercicio 2024 concluirá una vez que se apruebe en la Asamblea General
B25: Ordinaria del principio 2025.
B27: Les pedimos de realizar su pago lo antes posible.
B28: Les recordamos que tiene 15 días de pagar, en contrario 2% de mora será aplicado.
B30: Repartición de Cuota Extraordianaria Voto electronico del 09-04-24 | E30: =E21 -> 78142 | H30: Unidad | I30: Total monto | J30: Valor RD$ | K30: Total valor RD$ | L30: Repartición % | M30: Monto/cada
B31: Propietario | C31: UNIDAD | D31: % | E31: Monto a pagar | H31: 1 | I31: =E30 -> 78142 | J31: 3385038.8 | K31: 26236200 | L31: =J31/J38*100 -> 12.902169 | M31: =(I31*J31/K31) -> 10082.013 | N31: =M31 -> 10082.013
B32: Serge GUERRIN | C32: A-1 | D32: 0.129 | E32: =M31 -> 10082.013 | H32: 2 | I32: =E30 -> 78142 | J32: 3452215.8 | K32: 26236200 | L32: =J32/J38*100 -> 13.158216 | M32: =(I32*J32/K32) -> 10282.093 | N32: =M32 -> 10282.093
B33: Hervé METAYER | C33: A-2 | D33: 0.1316 | E33: =M32 -> 10282.093 | H33: 3 | I33: =E30 -> 78142 | J33: 4062206.5 | K33: 26236200 | L33: =J33/J38*100 -> 15.483212 | M33: =(I33*J33/K33) -> 12098.892 | N33: =M33 -> 12098.892
B34: Frédéric ONDELLA | C34: A-3 | D34: 0.1548 | E34: =M33 -> 12098.892 | H34: 4 | I34: =E30 -> 78142 | J34: 2069290.2 | K34: 26236200 | L34: =J34/J38*100 -> 7.8871565 | M34: =(I34*J34/K34) -> 6163.1818 | N34: =M34 -> 6163.1818
B35: Patricia FACQUET | C35: A-4 | D35: 0.0789 | E35: =M34 -> 6163.1818 | H35: 5 | I35: =E30 -> 78142 | J35: 2539129 | K35: 26236200 | L35: =J35/J38*100 -> 9.6779602 | M35: =(I35*J35/K35) -> 7562.5516 | N35: =M35 -> 7562.5516
B36: Gernot ENGER | C36: A-5 | D36: 0.0968 | E36: =M35 -> 7562.5516 | H36: 6 | I36: =E30 -> 78142 | J36: 4172168.8 | K36: 26236200 | L36: =J36/J38*100 -> 15.902336 | M36: =(I36*J36/K36) -> 12426.404 | N36: =M36 -> 12426.404
B37: Inversiones Ter 187 eirl (Karina SANTOS) | C37: A-6 | D37: 0.159 | E37: =M36 -> 12426.404 | H37: 7 | I37: =E30 -> 78142 | J37: 6556151 | K37: 26236200 | L37: =J37/J38*100 -> 24.98895 | M37: =(I37*J37/K37) -> 19526.866 | N37: =M37 -> 19526.866
B38: Jonathan HAZELTINE | C38: A-7 | D38: 0.2499 | E38: =M37 -> 19526.866 | J38: =SUM(J31:J37) -> 26236200 | L38: =SUM(L31:L37) -> 100 | M38: =SUM(M31:M37) -> 78142 | N38: =SUM(N31:N37) -> 78142
B39: Total | D39: =SUM(D32:D38) -> 1 | E39: =SUM(E32:E38) -> 78142

Sheet Pedido Exceptional - Agosto 24
A3: CONDOMINIO EL FRAMBOYANT
A4: Calle 30 de Marzo, Las Terrenas, Samaná, República Dominicana 32200
F6: Cuota Extraordinaria del 2024
B7: Pedido de fondo para trabajos emergencia agosto 2024
E9: Total
B10: Crismar Plomero - Material y mano de obra - Trabajo de plomería de emergencia: Cisterna y tuvo desagüé A5 - 15.07.2024 | E10: 12048
B11: Camion séptico 1 viaje - 15.07.2024 | E11: 7000
B12: Roberto Plomero - Trabajó en emergencia, tuvo desagüé A7 baños, similar A5 - 18.07.2024 | E12: 7500
B13: Andre Wemni - Trabajo de emergencia séptico - Zanja y tubos - 19.07.2024 | E13: 12298.45
B14: Camión de séptico 1 viaje - 19.07.2024 | E14: 7000
B15: Chavan Plomero - Trabajo de emergencia Séptico - Plomería, bomba y electricidad - 19.07.2024 | E15: 18369.23
B16: Crismar Plomero - Trabajó limpieza bomba pequeña, parqueo y colocar filtros en el tubo de 3",
B17: acostar la bomba cisterna para usar más del nivel útil del agua de la cisterna y regulador de presión de 100 PSI a 60 PSI como lo recomendó - 05.08 y el 08.08.2024 | E17: 7500
D21: Monto total | E21: =SUM(E10:E20) -> 71715.68
B22: Notas;
B23: Esta cuota extraordinaria es la manera provisional (presupuestos).
B24: La cierre contable del ejercicio 2024 concluirá una vez que se apruebe en la Asamblea General
B25: Ordinaria del principio 2025.
B27: Les pedimos de realizar su pago lo antes posible.
B28: Les recordamos que tiene 15 días de pagar, en contrario 2% de mora será aplicado.
B30: Repartición de Cuota Extraordianaria - Agosto 2024 | E30: =E21 -> 71715.68 | H30: Unidad | I30: Total monto | J30: Valor RD$ | K30: Total valor RD$ | L30: Repartición % | M30: Monto/cada
B31: Propietario | C31: UNIDAD | D31: % | E31: Monto a pagar | H31: 1 | I31: =E30 -> 71715.68 | J31: 3385038.8 | K31: 26236200 | L31: =J31/J38*100 -> 12.902169 | M31: =(I31*J31/K31) -> 9252.8781 | N31: =M31 -> 9252.8781
B32: Serge GUERRIN | C32: A-1 | D32: 0.129 | E32: =M31 -> 9252.8781 | H32: 2 | I32: =E30 -> 71715.68 | J32: 3452215.8 | K32: 26236200 | L32: =J32/J38*100 -> 13.158216 | M32: =(I32*J32/K32) -> 9436.5038 | N32: =M32 -> 9436.5038
B33: Hervé METAYER | C33: A-2 | D33: 0.1316 | E33: =M32 -> 9436.5038 | H33: 3 | I33: =E30 -> 71715.68 | J33: 4062206.5 | K33: 26236200 | L33: =J33/J38*100 -> 15.483212 | M33: =(I33*J33/K33) -> 11103.891 | N33: =M33 -> 11103.891
B34: Frédéric ONDELLA | C34: A-3 | D34: 0.1548 | E34: =M33 -> 11103.891 | H34: 4 | I34: =E30 -> 71715.68 | J34: 2069290.2 | K34: 26236200 | L34: =J34/J38*100 -> 7.8871565 | M34: =(I34*J34/K34) -> 5656.3279 | N34: =M34 -> 5656.3279
B35: Patricia FACQUET | C35: A-4 | D35: 0.0789 | E35: =M34 -> 5656.3279 | H35: 5 | I35: =E30 -> 71715.68 | J35: 2539129 | K35: 26236200 | L35: =J35/J38*100 -> 9.6779602 | M35: =(I35*J35/K35) -> 6940.6149 | N35: =M35 -> 6940.6149
B36: Gernot ENGER | C36: A-5 | D36: 0.0968 | E36: =M35 -> 6940.6149 | H36: 6 | I36: =E30 -> 71715.68 | J36: 4172168.8 | K36: 26236200 | L36: =J36/J38*100 -> 15.902336 | M36: =(I36*J36/K36) -> 11404.469 | N36: =M36 -> 11404.469
B37: Inversiones Ter 187 eirl (Karina SANTOS) | C37: A-6 | D37: 0.159 | E37: =M36 -> 11404.469 | H37: 7 | I37: =E30 -> 71715.68 | J37: 6556151 | K37: 26236200 | L37: =J37/J38*100 -> 24.98895 | M37: =(I37*J37/K37) -> 17920.996 | N37: =M37 -> 17920.996
B38: Jonathan HAZELTINE | C38: A-7 | D38: 0.2499 | E38: =M37 -> 17920.996 | J38: =SUM(J31:J37) -> 26236200 | L38: =SUM(L31:L37) -> 100 | M38: =SUM(M31:M37) -> 71715.68 | N38: =SUM(N31:N37) -> 71715.68
B39: Total | D39: =SUM(D32:D38) -> 1 | E39: =SUM(E32:E38) -> 71715.68

Sheet PedidoVotoElec-11-10
A3: CONDOMINIO EL FRAMBOYANT
A4: Calle 30 de Marzo, Las Terrenas, Samaná, República Dominicana 32200
B7: Pedido de fondo para Trabajos decidido en Voto electronico Del 11-10-2024
E9: Total
B10: Obra 1:
B11: Registrar condomino al RNC (500usd*61) | E11: 30500
B14: Obra 2:
B15: Obras luces parqueo A2-A3 | E15: 15059
B17: *Honorarios 10% para seguimientos y supervisores de trabajos | E17: =E15*0.1 -> 1505.9
D20: Monto total | E20: =SUM(E10:E19) -> 47064.9
B21: Notas;
B22: Esta cuota extraordinaria es la manera provisional (presupuestos).
B23: La cierre contable del ejercicio 2024 concluirá una vez que se apruebe en la Asamblea General
B24: Ordinaria del principio 2025.
B26: Les pedimos de realizar su pago lo antes posible.
B27: Les recordamos que tiene 15 días de pagar, en contrario 2% de mora será aplicado.
B29: Repartición de Cuota Extraordianaria Voto electronico del 09-04-24 | E29: =E20 -> 47064.9 | H29: Unidad | I29: Total monto | J29: Valor RD$ | K29: Total valor RD$ | L29: Repartición % | M29: Monto/cada
B30: Propietario | C30: UNIDAD | D30: % | E30: Monto a pagar | H30: 1 | I30: =E29 -> 47064.9 | J30: 3385038.8 | K30: 26236200 | L30: =J30/J37*100 -> 12.902169 | M30: =(I30*J30/K30) -> 6072.3928 | N30: =M30 -> 6072.3928
B31: Serge GUERRIN | C31: A-1 | D31: 0.129 | E31: =M30 -> 6072.3928 | H31: 2 | I31: =E29 -> 47064.9 | J31: 3452215.8 | K31: 26236200 | L31: =J31/J37*100 -> 13.158216 | M31: =(I31*J31/K31) -> 6192.901 | N31: =M31 -> 6192.901
B32: Hervé METAYER | C32: A-2 | D32: 0.1316 | E32: =M31 -> 6192.901 | H32: 3 | I32: =E29 -> 47064.9 | J32: 4062206.5 | K32: 26236200 | L32: =J32/J37*100 -> 15.483212 | M32: =(I32*J32/K32) -> 7287.1583 | N32: =M32 -> 7287.1583
B33: Frédéric ONDELLA | C33: A-3 | D33: 0.1548 | E33: =M32 -> 7287.1583 | H33: 4 | I33: =E29 -> 47064.9 | J33: 2069290.2 | K33: 26236200 | L33: =J33/J37*100 -> 7.8871565 | M33: =(I33*J33/K33) -> 3712.0823 | N33: =M33 -> 3712.0823
B34: Patricia FACQUET | C34: A-4 | D34: 0.0789 | E34: =M33 -> 3712.0823 | H34: 5 | I34: =E29 -> 47064.9 | J34: 2539129 | K34: 26236200 | L34: =J34/J37*100 -> 9.6779602 | M34: =(I34*J34/K34) -> 4554.9223 | N34: =M34 -> 4554.9223
B35: Gernot ENGER | C35: A-5 | D35: 0.0968 | E35: =M34 -> 4554.9223 | H35: 6 | I35: =E29 -> 47064.9 | J35: 4172168.8 | K35: 26236200 | L35: =J35/J37*100 -> 15.902336 | M35: =(I35*J35/K35) -> 7484.4187 | N35: =M35 -> 7484.4187
B36: Inversiones Ter 187 eirl (Karina SANTOS) | C36: A-6 | D36: 0.159 | E36: =M35 -> 7484.4187 | H36: 7 | I36: =E29 -> 47064.9 | J36: 6556151 | K36: 26236200 | L36: =J36/J37*100 -> 24.98895 | M36: =(I36*J36/K36) -> 11761.024 | N36: =M36 -> 11761.024
B37: Jonathan HAZELTINE | C37: A-7 | D37: 0.2499 | E37: =M36 -> 11761.024 | J37: =SUM(J30:J36) -> 26236200 | L37: =SUM(L30:L36) -> 100 | M37: =SUM(M30:M36) -> 47064.9 | N37: =SUM(N30:N36) -> 47064.9
B38: Total | D38: =SUM(D31:D37) -> 1 | E38: =SUM(E31:E37) -> 47064.9

Sheet PedidoVotoElec-09-12
A3: CONDOMINIO EL FRAMBOYANT
A4: Calle 30 de Marzo, Las Terrenas, Samaná, República Dominicana 32200
B7: Pedido de fondo para Trabajos decidido en Voto electronico Del 09-12-2024
E9: Total
B10: Obra 1:
B11: Trabajo de caños para el agua del techo principal | E11: 53235
B13: *Honorarios 10% para seguimientos y supervision de trabajos | E13: =E11*0.1 -> 5323.5
B15: Obra 2:
B16: Filtracion pared este, edificio de los apartamentos A3-A6 y parte de A7 y A8 | E16: 48600
B18: *Honorarios 10% para seguimientos y supervision de trabajos | E18: =E16*0.1 -> 4860
D21: Monto total | E21: =SUM(E10:E20) -> 112018.5
B22: Notas;
B23: Esta cuota extraordinaria es la manera provisional (presupuestos).
B24: La cierre contable del ejercicio 2024 concluirá una vez que se apruebe en la Asamblea General
B25: Ordinaria del principio 2025.
B27: Les pedimos de realizar su pago lo antes posible.
B28: Les recordamos que tiene 15 días de pagar, en contrario 2% de mora será aplicado.
B30: Repartición de Cuota Extraordianaria Voto electronico del 09-04-24 | E30: =E21 -> 112018.5 | H30: Unidad | I30: Total monto | J30: Valor RD$ | K30: Total valor RD$ | L30: Repartición % | M30: Monto/cada
B31: Propietario | C31: UNIDAD | D31: % | E31: Monto a pagar | H31: 1 | I31: =E30 -> 112018.5 | J31: 3385038.8 | K31: 26236200 | L31: =J31/J38*100 -> 12.902169 | M31: =(I31*J31/K31) -> 14452.816 | N31: =M31 -> 14452.816
B32: Serge GUERRIN | C32: A-1 | D32: 0.129 | E32: =M31 -> 14452.816 | H32: 2 | I32: =E30 -> 112018.5 | J32: 3452215.8 | K32: 26236200 | L32: =J32/J38*100 -> 13.158216 | M32: =(I32*J32/K32) -> 14739.636 | N32: =M32 -> 14739.636
B33: Hervé METAYER | C33: A-2 | D33: 0.1316 | E33: =M32 -> 14739.636 | H33: 3 | I33: =E30 -> 112018.5 | J33: 4062206.5 | K33: 26236200 | L33: =J33/J38*100 -> 15.483212 | M33: =(I33*J33/K33) -> 17344.062 | N33: =M33 -> 17344.062
B34: Frédéric ONDELLA | C34: A-3 | D34: 0.1548 | E34: =M33 -> 17344.062 | H34: 4 | I34: =E30 -> 112018.5 | J34: 2069290.2 | K34: 26236200 | L34: =J34/J38*100 -> 7.8871565 | M34: =(I34*J34/K34) -> 8835.0744 | N34: =M34 -> 8835.0744
B35: Patricia FACQUET | C35: A-4 | D35: 0.0789 | E35: =M34 -> 8835.0744 | H35: 5 | I35: =E30 -> 112018.5 | J35: 2539129 | K35: 26236200 | L35: =J35/J38*100 -> 9.6779602 | M35: =(I35*J35/K35) -> 10841.106 | N35: =M35 -> 10841.106
B36: Gernot ENGER | C36: A-5 | D36: 0.0968 | E36: =M35 -> 10841.106 | H36: 6 | I36: =E30 -> 112018.5 | J36: 4172168.8 | K36: 26236200 | L36: =J36/J38*100 -> 15.902336 | M36: =(I36*J36/K36) -> 17813.559 | N36: =M36 -> 17813.559
B37: Inversiones Ter 187 eirl (Karina SANTOS) | C37: A-6 | D37: 0.159 | E37: =M36 -> 17813.559 | H37: 7 | I37: =E30 -> 112018.5 | J37: 6556151 | K37: 26236200 | L37: =J37/J38*100 -> 24.98895 | M37: =(I37*J37/K37) -> 27992.247 | N37: =M37 -> 27992.247
B38: Jonathan HAZELTINE | C38: A-7 | D38: 0.2499 | E38: =M37 -> 27992.247 | J38: =SUM(J31:J37) -> 26236200 | L38: =SUM(L31:L37) -> 100 | M38: =SUM(M31:M37) -> 112018.5 | N38: =SUM(N31:N37) -> 112018.5
B39: Total | D39: =SUM(D32:D38) -> 1 | E39: =SUM(E32:E38) -> 112018.5

Sheet Pedido Exceptional - ENERO2025
A3: CONDOMINIO EL FRAMBOYANT
A4: Calle 30 de Marzo, Las Terrenas, Samaná, República Dominicana 32200
F6: Cuota Extraordinaria del 2025
B7: Pedido de fondo para trabajos emergencia 2025
E9: Total
B10: Compra de Bomba de agua sumergible+ Materiales | E10: 36205.11
B12: Compra de 6 Camiones de agua (Averia inapa) | E12: 6000
D14: Monto total | E14: =SUM(E10:E13) -> 42205.11
B15: Notas;
B16: Esta cuota extraordinaria es la manera provisional (presupuestos).
B17: La cierre contable del ejercicio 2024 concluirá una vez que se apruebe en la Asamblea General
B18: Ordinaria del principio 2025.
B20: Les pedimos de realizar su pago lo antes posible.
B21: Les recordamos que tiene 15 días de pagar, en contrario 2% de mora será aplicado.
B23: Repartición de Cuota Extraordianaria - Agosto 2024 | E23: =E14 -> 42205.11 | H23: Unidad | I23: Total monto | J23: Valor RD$ | K23: Total valor RD$ | L23: Repartición % | M23: Monto/cada
B24: Propietario | C24: UNIDAD | D24: % | E24: Monto a pagar | H24: 1 | I24: =E23 -> 42205.11 | J24: 3385038.8 | K24: 26236200 | L24: =J24/J31*100 -> 12.902169 | M24: =(I24*J24/K24) -> 5445.3745 | N24: =M24 -> 5445.3745
B25: Serge GUERRIN | C25: A-1 | D25: 0.129 | E25: =M24 -> 5445.3745 | H25: 2 | I25: =E23 -> 42205.11 | J25: 3452215.8 | K25: 26236200 | L25: =J25/J31*100 -> 13.158216 | M25: =(I25*J25/K25) -> 5553.4394 | N25: =M25 -> 5553.4394
B26: Hervé METAYER | C26: A-2 | D26: 0.1316 | E26: =M25 -> 5553.4394 | H26: 3 | I26: =E23 -> 42205.11 | J26: 4062206.5 | K26: 26236200 | L26: =J26/J31*100 -> 15.483212 | M26: =(I26*J26/K26) -> 6534.7067 | N26: =M26 -> 6534.7067
B27: Frédéric ONDELLA | C27: A-3 | D27: 0.1548 | E27: =M26 -> 6534.7067 | H27: 4 | I27: =E23 -> 42205.11 | J27: 2069290.2 | K27: 26236200 | L27: =J27/J31*100 -> 7.8871565 | M27: =(I27*J27/K27) -> 3328.7831 | N27: =M27 -> 3328.7831
B28: Patricia FACQUET | C28: A-4 | D28: 0.0789 | E28: =M27 -> 3328.7831 | H28: 5 | I28: =E23 -> 42205.11 | J28: 2539129 | K28: 26236200 | L28: =J28/J31*100 -> 9.6779602 | M28: =(I28*J28/K28) -> 4084.5937 | N28: =M28 -> 4084.5937
B29: Gernot ENGER | C29: A-5 | D29: 0.0968 | E29: =M28 -> 4084.5937 | H29: 6 | I29: =E23 -> 42205.11 | J29: 4172168.8 | K29: 26236200 | L29: =J29/J31*100 -> 15.902336 | M29: =(I29*J29/K29) -> 6711.5986 | N29: =M29 -> 6711.5986
B30: Inversiones Ter 187 eirl (Karina SANTOS) | C30: A-6 | D30: 0.159 | E30: =M29 -> 6711.5986 | H30: 7 | I30: =E23 -> 42205.11 | J30: 6556151 | K30: 26236200 | L30: =J30/J31*100 -> 24.98895 | M30: =(I30*J30/K30) -> 10546.614 | N30: =M30 -> 10546.614
B31: Jonathan HAZELTINE | C31: A-7 | D31: 0.2499 | E31: =M30 -> 10546.614 | J31: =SUM(J24:J30) -> 26236200 | L31: =SUM(L24:L30) -> 100 | M31: =SUM(M24:M30) -> 42205.11 | N31: =SUM(N24:N30) -> 42205.11
B32: Total | D32: =SUM(D25:D31) -> 1 | E32: =SUM(E25:E31) -> 42205.11

Sheet Presupuesto 2024 Aprobado
A2: CONDOMINIO EL FRAMBOYANT
A3: Calle 30 de Marzo, Las Terrenas, Samaná, República Dominicana 32200
F5: Periodo de 01/01 hasta 31/12/2024
B6: Presupuesto Provisional 2024 aprobado por la AGO del 13/02/2024
C8: Por mes | D8: Meses | E8: Anual
B9: INAPA/Agua | C9: 3600 | D9: 12 | E9: =C9*D9 -> 43200
B10: Agua (camión de agua) | C10: 1500 | D10: 12 | E10: =C10*D10 -> 18000
B11: LUZ Y FUERZA / Electricidad | C11: 800 | D11: 12 | E11: =C11*D11 -> 9600
B12: Reparaciones / Mantenimientos | C12: 3500 | D12: 12 | E12: =C12*D12 -> 42000
B13: Basura / Recogida mensual | C13: 1000 | D13: 12 | E13: =C13*D13 -> 12000
B14: Honorario Administrador | C14: 15000 | D14: 12 | E14: =C14*D14 -> 180000
B15: Gastos bancario | C15: 150 | D15: 12 | E15: =C15*D15 -> 1800
B16: Trabajo tuberías drenaje de agua pluvial (monto adicional) | E16: 30237.82
B17: Seguro Incendio y R.C. (20/11/2024-2025) | E17: 162400
B18: Total Anual Gastos Provisional 2024 | C18: =SUM(C9:C17) -> 25550 | E18: =SUM(E9:E17) -> 499237.82
B19: Fondo de Reservas (para completar $80,000) | E19: 16030.55
B20: * Fondo de Reservas (diferencia prevista por cancelación trabajo medidor de agua) | C20: (* La diferencia exacta será tomada cuenta al cierre del año 2024) | E20: 23969.45
B21: Total Fondo de Reservas 2024 | E21: =E19+E20 -> 40000
E22: =E18+E21 -> 539237.82
B23: Se pedirá trimestralmente (4 veces) : $124,809.46RD y $10,000.00RD Total $134,809.46RD
B24: Nota: Tenemos una nota de crédito (materiales) con Ferretería The Home Acosta Polanco
B25: con un importe de $14,514.18RD (aproximadamente) | H25: Calculo presupuesto 2024
B26: Repartición de gasto común provisional 2024: | D26: por año | E26: =E18 -> 499237.82 | H26: Unidad | I26: Total monto | J26: Valor RD$ | K26: Total valor RD$ | L26: Repartición % | M26: Monto/cada
B27: Propietario | C27: UNIDAD | D27: % | E27: Monto a pagar | H27: 1 | I27: =E26 -> 499237.82 | J27: 3386200 | K27: 26236200 | L27: =(J27/J34)*100 -> 12.906595 | M27: =(I27*J27/K27) -> 64434.602 | N27: 64434.6
B28: Serge GUERRIN | C28: A-1 | D28: 0.129 | E28: 64434.6 | H28: 2 | I28: =E26 -> 499237.82 | J28: 3453400 | K28: 26236200 | L28: =(J28/J34)*100 -> 13.162729 | M28: =(I28*J28/K28) -> 65713.323 | N28: 65713.32
B29: Herve METAYER | C29: A-2 | D29: 0.1316 | E29: 65713.32 | H29: 3 | I29: =E26 -> 499237.82 | J29: 4063600 | K29: 26236200 | L29: =(J29/J34)*100 -> 15.488523 | M29: =(I29*J29/K29) -> 77324.567 | N29: 77324.57
B30: Frédéric ONDELLA | C30: A-3 | D30: 0.1549 | E30: 77324.57 | H30: 4 | I30: =E26 -> 499237.82 | J30: 2061000 | K30: 26236200 | L30: =(J30/J34)*100 -> 7.8555584 | M30: =(I30*J30/K30) -> 39217.918 | N30: 39217.92
B31: Patricia FACQUET | C31: A-4 | D31: 0.0786 | E31: 39217.92 | H31: 5 | I31: =E26 -> 499237.82 | J31: 2540000 | K31: 26236200 | L31: =(J31/J34)*100 -> 9.6812801 | M31: =(I31*J31/K31) -> 48332.612 | N31: 48332.61
B32: Gernot ENGER | C32: A-5 | D32: 0.0968 | E32: 48332.61 | H32: 6 | I32: =E26 -> 499237.82 | J32: 4173600 | K32: 26236200 | L32: =(J32/J34)*100 -> 15.907792 | M32: =(I32*J32/K32) -> 79417.712 | N32: 79417.71
B33: Inversiones Ter 187 eirl (Karina SANTOS) | C33: A-6 | D33: 0.1591 | E33: 79417.71 | H33: 7 | I33: =E26 -> 499237.82 | J33: 6558400 | K33: 26236200 | L33: =(J33/J34)*100 -> 24.997523 | M33: =(I33*J33/K33) -> 124797.09 | N33: 124797.09
B34: Jonathan HAZELTINE | C34: A-7 | D34: 0.25 | E34: 124797.09 | J34: =SUM(J27:J33) -> 26236200 | L34: =SUM(L27:L33) -> 100 | M34: =SUM(M27:M33) -> 499237.82 | N34: =SUM(N27:N33) -> 499237.82
B35: Total | D35: =SUM(D28:D34) -> 1 | E35: =SUM(E28:E34) -> 499237.82
H36: Calculo Fondo de Reservas 2024
B37: Repartición de Fondo de Reservas 2024: | D37: por año | E37: =E19+E20 -> 40000 | H37: Unidad | I37: Total monto | J37: Valor RD$ | K37: Total valor RD$ | L37: Repartición % | M37: Monto/cada
B38: Propietario | C38: UNIDAD | D38: % | E38: Monto a pagar | H38: 1 | I38: =E37 -> 40000 | J38: 3386200 | K38: 26236200 | L38: =(J38/J45)*100 -> 12.906595 | M38: =(I38*J38/K38) -> 5162.6379 | N38: 5162.64
B39: Serge GUERRIN | C39: A-1 | D39: 0.129 | E39: 5162.64 | H39: 2 | I39: =E37 -> 40000 | J39: 3453400 | K39: 26236200 | L39: =(J39/J45)*100 -> 13.162729 | M39: =(I39*J39/K39) -> 5265.0917 | N39: 5265.09
B40: Herve METAYER | C40: A-2 | D40: 0.1316 | E40: 5265.09 | H40: 3 | I40: =E37 -> 40000 | J40: 4063600 | K40: 26236200 | L40: =(J40/J45)*100 -> 15.488523 | M40: =(I40*J40/K40) -> 6195.4094 | N40: 6195.41
B41: Frédéric ONDELLA | C41: A-3 | D41: 0.1549 | E41: 6195.41 | H41: 4 | I41: =E37 -> 40000 | J41: 2061000 | K41: 26236200 | L41: =(J41/J45)*100 -> 7.8555584 | M41: =(I41*J41/K41) -> 3142.2233 | N41: 3142.22
B42: Patricia FACQUET | C42: A-4 | D42: 0.0786 | E42: 3142.22 | H42: 5 | I42: =E37 -> 40000 | J42: 2540000 | K42: 26236200 | L42: =(J42/J45)*100 -> 9.6812801 | M42: =(I42*J42/K42) -> 3872.512 | N42: 3872.51
B43: Gernot ENGER | C43: A-5 | D43: 0.0968 | E43: 3872.51 | H43: 6 | I43: =E37 -> 40000 | J43: 4173600 | K43: 26236200 | L43: =(J43/J45)*100 -> 15.907792 | M43: =(I43*J43/K43) -> 6363.1166 | N43: 6363.12
B44: Inversiones Ter 187 eirl (Karina SANTOS) | C44: A-6 | D44: 0.1591 | E44: 6363.12 | H44: 7 | I44: =E37 -> 40000 | J44: 6558400 | K44: 26236200 | L44: =(J44/J45)*100 -> 24.997523 | M44: =(I44*J44/K44) -> 9999.009 | N44: 9999.01
B45: Jonathan HAZELTINE | C45: A-7 | D45: 0.25 | E45: 9999.01 | J45: =SUM(J38:J44) -> 26236200 | L45: =SUM(L38:L44) -> 100 | M45: =SUM(M38:M44) -> 40000 | N45: =SUM(N38:N44) -> 40000
B46: Total | D46: =SUM(D39:D45) -> 1 | E46: =SUM(E39:E45) -> 40000
H47: Calculo cierre del 2023
C48: MONTO TRIMESTRE 2024 | H48: Unidad | I48: Total monto | J48: Valor RD$ | K48: Total valor RD$ | L48: Repartición % | M48: Monto/cada
B49: Unidad | C49: Gastos | D49: Fdo. Reservas | E49: Total | H49: 1 | I49: 807965.5 | J49: 3386200 | K49: 26236200 | L49: =(J49/J56)*100 -> 12.906595 | M49: =(I49*J49/K49) -> 104280.83 | N49: 104280.83
B50: A-1 | C50: =E28/4 -> 16108.65 | D50: =E39/4 -> 1290.66 | E50: =C50+D50 -> 17399.31 | H50: 2 | I50: 807965.5 | J50: 3453400 | K50: 26236200 | L50: =(J50/J56)*100 -> 13.162729 | M50: =(I50*J50/K50) -> 106350.31 | N50: 106350.31
B51: A-2 | C51: =E29/4 -> 16428.33 | D51: =E40/4 -> 1316.2725 | E51: =C51+D51 -> 17744.603 | H51: 3 | I51: 807965.5 | J51: 4063600 | K51: 26236200 | L51: =(J51/J56)*100 -> 15.488523 | M51: =(I51*J51/K51) -> 125141.93 | N51: 125141.93
B52: A-3 | C52: =E30/4 -> 19331.143 | D52: =E41/4 -> 1548.8525 | E52: =C52+D52 -> 20879.995 | H52: 4 | I52: 807965.5 | J52: 2061000 | K52: 26236200 | L52: =(J52/J56)*100 -> 7.8555584 | M52: =(I52*J52/K52) -> 63470.201 | N52: 63470.2
B53: A-4 | C53: =E31/4 -> 9804.48 | D53: =E42/4 -> 785.555 | E53: =C53+D53 -> 10590.035 | H53: 5 | I53: 807965.5 | J53: 2540000 | K53: 26236200 | L53: =(J53/J56)*100 -> 9.6812801 | M53: =(I53*J53/K53) -> 78221.403 | N53: 78221.4
B54: A-5 | C54: =E32/4 -> 12083.153 | D54: =E43/4 -> 968.1275 | E54: =C54+D54 -> 13051.28 | H54: 6 | I54: 807965.5 | J54: 4173600 | K54: 26236200 | L54: =(J54/J56)*100 -> 15.907792 | M54: =(I54*J54/K54) -> 128529.47 | N54: 128529.47
B55: A-6 | C55: =E33/4 -> 19854.428 | D55: =E44/4 -> 1590.78 | E55: =C55+D55 -> 21445.208 | H55: 7 | I55: 807965.5 | J55: 6558400 | K55: 26236200 | L55: =(J55/J56)*100 -> 24.997523 | M55: =(I55*J55/K55) -> 201971.36 | N55: 201971.36
B56: A-7 | C56: =E34/4 -> 31199.272 | D56: =E45/4 -> 2499.7525 | E56: =C56+D56 -> 33699.025 | J56: =SUM(J49:J55) -> 26236200 | L56: =SUM(L49:L55) -> 100 | M56: =SUM(M49:M55) -> 807965.5 | N56: =SUM(N49:N55) -> 807965.5
C57: =SUM(C50:C56) -> 124809.46 | D57: =SUM(D50:D56) -> 10000 | E57: =SUM(E50:E56) -> 134809.46
H58: Calculo cierre del 2023
H59: Unidad | I59: Total monto | J59: Valor RD$ | K59: Total valor RD$ | L59: Repartición % | M59: Monto/cada
H60: 1 | I60: 40000 | J60: 3386200 | K60: 26236200 | L60: =(J60/J67)*100 -> 12.906595 | M60: =(I60*J60/K60) -> 5162.6379 | N60: 5162.64
H61: 2 | I61: 40000 | J61: 3453400 | K61: 26236200 | L61: =(J61/J67)*100 -> 13.162729 | M61: =(I61*J61/K61) -> 5265.0917 | N61: 5265.09
H62: 3 | I62: 40000 | J62: 4063600 | K62: 26236200 | L62: =(J62/J67)*100 -> 15.488523 | M62: =(I62*J62/K62) -> 6195.4094 | N62: 6195.41
H63: 4 | I63: 40000 | J63: 2061000 | K63: 26236200 | L63: =(J63/J67)*100 -> 7.8555584 | M63: =(I63*J63/K63) -> 3142.2233 | N63: 3142.22
H64: 5 | I64: 40000 | J64: 2540000 | K64: 26236200 | L64: =(J64/J67)*100 -> 9.6812801 | M64: =(I64*J64/K64) -> 3872.512 | N64: 3872.51
H65: 6 | I65: 40000 | J65: 4173600 | K65: 26236200 | L65: =(J65/J67)*100 -> 15.907792 | M65: =(I65*J65/K65) -> 6363.1166 | N65: 6363.12
H66: 7 | I66: 40000 | J66: 6558400 | K66: 26236200 | L66: =(J66/J67)*100 -> 24.997523 | M66: =(I66*J66/K66) -> 9999.009 | N66: 9999.01
J67: =SUM(J60:J66) -> 26236200 | L67: =SUM(L60:L66) -> 100 | M67: =SUM(M60:M66) -> 40000 | N67: =SUM(N60:N66) -> 40000

Sheet A1
A3: CONDOMINIO EL FRAMBOYANT
A4: Calle 30 de Marzo, Las Terrenas, Samaná, República Dominicana 32200
B5: Apartamento A-1
B6: Serge GUERIN | C6: Fecha limite de pago : 23.01.25
B7: serge47.guerin@gmail.com
G9: Periodo de 01/01/2024 hasta 07/01/2025
B10: Estado de cuenta
B12: Descripción | C12: Fecha | D12: Débito | E12: Crédito | F12: Saldo
B13: Pago Serge GUERIN | C13: 45117 | E13: 5900 | F13: =E13 -> 5900
B14: Pago Serge GUERIN | C14: 45117 | E14: 5901 | F14: =F13-D14+E14 -> 11801
B15: Pago Serge GUERIN | C15: 45205 | E15: 25100 | F15: =F14-D15+E15 -> 36901
B16: Pago Serge GUERIN | C16: 45266 | E16: 48373 | F16: =F15-D16+E16 -> 85274
B17: Pago Serge GUERIN | C17: 45266 | E17: 1341 | F17: =F16-D17+E17 -> 86615
B18: Cargo 2% del $26 548.93 (Reglamento Art.33-d) | C18: 45266 | D18: 530.98 | F18: =F17-D18+E18 -> 86084.02
B19: SALDO ANTERIOR | C19: 45657 | F19: 86084.02
B20: Cargo 2% del $26 548.93 (Reglamento Art.33-d) | C20: 45297 | D20: 530.98 | F20: =F18-D20+E20 -> 85553.04
B21: Pedido de fondo – cuota extraordinaria AGE del 12-01-2024 | C21: 45321 | D21: 20110.01 | F21: =F20-D21+E21 -> 65443.03
B22: Honorario del Alguacil LT para la Notificación de deudas | C22: 45330 | D22: 4000 | F22: =F21-D22+E22 -> 61443.03
B23: Pago Serge GUERIN (47 720,90+72,56) | C23: 45331 | E23: 47720.9 | F23: =F22-D23+E23 -> 109163.93
B24: Gastos Total año 2023 (Aprobado en AGO del 13 febrero 2024) | C24: 45335 | D24: 104280.83 | F24: =F23-D24+E24 -> 4883.1
B25: Fondo de Reservas 2023 (Pedido del 01/10/2023 - Total $40,000RD) | C25: 45335 | D25: 5162.64 | F25: =F24-D25+E25 -> -279.54
B26: 1er Trimestre 2024 (Enero – Marzo) / Gastos común provisional | C26: 45336 | D26: 16108.65 | F26: =F25-D26+E26 -> -16388.19
B27: 1er Trimestre 2024 (Enero – Marzo) / Fondo de Reservas 2024 | C27: 45336 | D27: 1290.66 | F27: =F26-D27+E27 -> -17678.85
B28: Pago Serge GUERIN | C28: 45339 | E28: 35005.6 | F28: =F27-D28+E28 -> 17326.75
B29: Rectificación error del 09/02/2024 | C29: 45343 | E29: 72.56 | F29: =F28-D29+E29 -> 17399.31
B30: 2do Trimestre 2024 (Abril – Junio) / Gastos común provisional | C30: 45383 | D30: 16108.65 | F30: =F29-D30+E30 -> 1290.66
B31: 2do Trimestre 2024 (Abril – Junio) / Fondo de Reservas 2024 | C31: 45383 | D31: 1290.66 | F31: =F30-D31+E31 -> 1.978151e-11
B32: Pedido de fondo – cuota extraordinaria Voto electronico del 09-04-2024 | C32: 45397 | D32: 10082.013 | F32: =F31-D32+E32 -> -10082.013
B33: Cargo 2% del $10,082.01 (Reglamento Art.33-d) | C33: 45418 | D33: =D32*2% -> 201.64025 | F33: =F32-D33+E33 -> -10283.653
B34: Diferencia presupuesto pared cerca y gastos reales de la obra al gasto unico A1-AGE 12.01.24 orden 6 | C34: 45425 | D34: 24574 | F34: =F33-D34+E34 -> -34857.653
B35: Cargo 2% de $24,574 (Reglamento Art.33-d)Age 12.01.24 orden 6 | C35: 45443 | D35: =D34*2% -> 491.48 | F35: =F34-D35+E35 -> -35349.133
B36: Cargo 2% del $10,082.01 (Reglamento Art.33-d) voto del 09.04.24 | C36: 45449 | D36: =D32*2% -> 201.64025 | F36: =F35-D36+E36 -> -35550.773
B37: Cargo 2% de $24,574 (Reglamento Art.33-d)Age 12.01.24 orden 6 | C37: 45473 | D37: =D34*2% -> 491.48 | F37: =F36-D37+E37 -> -36042.253
B38: 3er Trimestre 2024 (Julio– Septiembre) / Gastos común provisional | C38: 45474 | D38: ='Presupuesto 2024 Aprobado'!C50 -> 16108.65 | F38: =F37-D38+E38 -> -52150.903
B39: 3er Trimestre 2024 (Julio– Septiembre) / Fondo de Reservas 2024 | C39: 45474 | D39: ='Presupuesto 2024 Aprobado'!D50 -> 1290.66 | F39: =F38-D39+E39 -> -53441.563
B40: Cargo 2% del $10,082.01 (Reglamento Art.33-d) voto del 09.04.24 | C40: 45479 | D40: =D32*2% -> 201.64025 | F40: =F39-D40+E40 -> -53643.203
B41: Cargo 2% del $16,108.65+1,290.66 Tercer trimestre (Reglamento Art.33-d) | C41: 45490 | D41: 347.98 | F41: =F40-D41+E41 -> -53991.183
B42: Cargo 2% de $24,574 (Reglamento Art.33-d)Diff Presupuesto pared cerca | C42: 45504 | D42: =D34*2% -> 491.48 | F42: =F41-D42+E42 -> -54482.663
B43: Cargo 2% del $10,082.01 (Reglamento Art.33-d), pedido de fondo cuota extraordinaria del 09.04.34 | C43: 45510 | D43: =D32*2% -> 201.64025 | F43: =F42-D43+E43 -> -54684.304
B44: Pedido de fondo – cuota excepcional agosto-2024 | C44: 45510 | D44: 9252.88 | F44: =F43-D44+E44 -> -63937.184
B45: Pago Serge GUERIN | C45: 45510 | E45: 17400 | F45: =F44-D45+E45 -> -46537.184
B46: Cargo 2% de $24,574 (Reglamento Art.33-d)Diff Presupuesto pared cerca | C46: 45535 | D46: =D34*2% -> 491.48 | F46: =F45-D46+E46 -> -47028.664
B47: Cargo 2% del $10,082.01 (Reglamento Art.33-d), pedido de fondo cuota extraordinaria del 09.04.34 | C47: 45541 | D47: 201.64 | F47: =F46-D47+E47 -> -47230.304
B48: Cargo 2% del $9,252.88(Reglamento Art.33-d) Pedido de fondo cuota excepcional Agosto-2024 | C48: 45541 | D48: =D44*2% -> 185.0576 | F48: =F47-D48+E48 -> -47415.361
B49: Cargo 2% de $24,574 (Reglamento Art.33-d)Diff Presupuesto pared cerca | C49: 45565 | D49: =D34*2% -> 491.48 | F49: =F48-D49+E49 -> -47906.841
B50: 4to Trimestre 2024 (Octubre– Diciembre) / Gastos común provisional | C50: 45566 | D50: ='Presupuesto 2024 Aprobado'!C50 -> 16108.65 | F50: =F49-D50+E50 -> -64015.491
B51: 4to Trimestre 2024 (Octubre– Diciembre) / Fondo de Reservas 2024 | C51: 45566 | D51: ='Presupuesto 2024 Aprobado'!D50 -> 1290.66 | F51: =F50-D51+E51 -> -65306.151
B52: Pago Serge GUERIN | C52: 45572 | E52: 16108.65 | F52: =F51-D52+E52 -> -49197.501
B53: Cargo 2% del $10,082.01 (Reglamento Art.33-d) voto del 09.04.24 | C53: 45572 | D53: 201.64 | F53: =F52-D53+E53 -> -49399.141
B54: Cargo 2% del $9,252.88(Reglamento Art.33-d) Pedido de fondo cuota excepcional Agosto-2024 | C54: 45572 | D54: 185.96 | F54: =F53-D54+E54 -> -49585.101
B55: Cargo 2% de 1,290.66 4To trimestre (Reglamento Art.33-d) | C55: 45582 | D55: =D51*2% -> 25.8132 | F55: =F54-D55+E55 -> -49610.915
B56: Cargo 2% de $24,574 (Reglamento Art.33-d)Diff Presupuesto pared cerca | C56: 45595 | D56: 491.48 | F56: =F55-D56+E56 -> -50102.395
B57: Cargo 2% del $10,082.01 (Reglamento Art.33-d) voto del 09.04.24 | C57: 45603 | D57: 201.64 | F57: =F56-D57+E57 -> -50304.035
B58: Cargo 2% del $9,252.88(Reglamento Art.33-d) Pedido de fondo cuota excepcional Agosto-2024 | C58: 45603 | D58: 185.96 | F58: =F57-D58+E58 -> -50489.995
B59: Cargo 2% de 1,290.66 4To trimestre (Reglamento Art.33-d) | C59: 45613 | D59: 25.81 | F59: =F58-D59+E59 -> -50515.805
B60: Cargo 2% de $24,574 (Reglamento Art.33-d)Diff Presupuesto pared cerca | C60: 45626 | D60: 491.48 | F60: =F59-D60+E60 -> -51007.285
B61: Cargo 2% del $10,082.01 (Reglamento Art.33-d) voto del 09.04.24 | C61: 45633 | D61: 201.64 | F61: =F60-D61+E61 -> -51208.925
B62: Cargo 2% del $9,252.88(Reglamento Art.33-d) Pedido de fondo cuota excepcional Agosto-2024 | C62: 45633 | D62: 185.96 | F62: =F61-D62+E62 -> -51394.885
B63: Cargo 2% de 1,290.66 4To trimestre (Reglamento Art.33-d) | C63: 45643 | D63: 25.81 | F63: =F62-D63+E63 -> -51420.695
B64: Cargo 2% de $24,574 (Reglamento Art.33-d)Diff Presupuesto pared cerca | C64: 45656 | D64: 491.48 | F64: =F63-D64+E64 -> -51912.175
B65: Pedido de fondo – cuota extraordinaria Voto electronico del 11-10-2024 | C65: 45664 | D65: ='PedidoVotoElec-11-10'!E31 -> 6072.3928 | F65: =F64-D65+E65 -> -57984.567
B66: Pedido de fondo – cuota extraordinaria Voto electronico del 09-12-2024 | C66: 45664 | D66: ='PedidoVotoElec-09-12'!E32 -> 14452.816 | F66: =F65-D66+E66 -> -72437.383
B67: Pedido Excepcional- Enero 2025 | C67: 45664 | D67: ='Pedido Exceptional - ENERO2025'!E25 -> 5445.3745 | F67: =F66-D67+E67 -> -77882.758
C68: TOTAL A1-GUERRIN | D68: =SUM(D13:D67) -> 280805.47 | E68: =SUM(E13:E67) -> 202922.71 | F68: =E68-D68 -> -77882.758
B71: GASTOS PRIVADO - Aparte de los gastos comunes
B72: Cargo administrador recordatorio pago 15 dias despues venc.Pedido de fondo – cuota extraordinaria Voto electronico del 09-04-2024 $10,082.01 | C72: 45418 | D72: -1000
B73: Cargo administrador recordatorio pago 15 dias despues venc Cuota diff presupuesto gastos reales 12.01.24 - Orden6) | C73: 45443 | D73: -1000
B74: Cargo administrador segundo recordatorio pago 45 dias despues venc. (Pedido 2do Trimiestre Abril-Junio 2024 | C74: 45473 | D74: -3000
B75: Cargo administrador segundo recordatorio pago 45 dias despues venc. (Cuota diff presupuesto gastos reales 12.01.24 - Orden6) | C75: 45473 | D75: -3000
B76: Honorarios Alguacil-Notificacion de pago | C76: 45481 | D76: -5000
B77: Cargo administrador recordatorio Pedido Excepcional Agosto-24 | C77: 45540 | D77: -1000
B80: total | D80: =SUM(D72:D78) -> -14000
F82: =F68+D80 -> -91882.758
B83: Nota Importante: | F83: TOTAL en debito
B84: Su estado de cuenta está en manera provisional hasta que se cierran las contabilidades del 2024.
B86: Banco POPULAR
B87: Cuenta Corriente - Sra YUNAIRY ENCARNACION - Cedula 134-0005411-3
B88: Cuenta : 0839787280
B89: Pesos

Sheet A2
A3: CONDOMINIO EL FRAMBOYANT
A4: Calle 30 de Marzo, Las Terrenas, Samaná, República Dominicana 32200
B5: Apartamento A-2
B6: Hervé METAYER / Corine JEAN | D6: Fecha limite de pago : 23.01.25
B7: hmetayer.business@gmail.com; corine.2021@outlook.fr
G9: Periodo de 01/01/2024 hasta 07/01/2025
B10: Estado de cuenta
B12: Descripción | C12: Fecha | D12: Débito | E12: Crédito | F12: Saldo
B13: Pago METAYER-JEAN | C13: 45117 | E13: 5900 | F13: =E13 -> 5900
B14: Pago METAYER-JEAN | C14: 45117 | E14: 6015 | F14: =F13-D14+E14 -> 11915
B15: Pago METAYER-JEAN | C15: 45210 | E15: 25600 | F15: =F14-D15+E15 -> 37515
B16: Pago METAYER-JEAN | C16: 45262 | E16: 78000 | F16: =F15-D16+E16 -> 115515
B17: SALDO ANTERIOR | C17: 45291 | F17: =F16-D17+E17 -> 115515
B18: Pedido de fondo – cuota extraordinaria AGE del 12-01-2024 | C18: 45321 | D18: 20509.1 | F18: =F17-D18+E18 -> 95005.9
B19: Gastos Total año 2023 (Aprobado en AGO del 13 febrero 2024) | C19: 45335 | D19: 106350.31 | F19: =F18-D19+E19 -> -11344.41
B20: Fondo de Reservas 2023 (Pedido del 01/10/2023 - Total $40,000RD) | C20: 45335 | D20: 5265.09 | F20: =F19-D20+E20 -> -16609.5
B21: 1er Trimestre 2024 (Enero – Marzo) / Gastos común provisional | C21: 45336 | D21: 16428.33 | F21: =F20-D21+E21 -> -33037.83
B22: 1er Trimestre 2024 (Enero – Marzo) / Fondo de Reservas 2024 | C22: 45336 | D22: 1316.27 | F22: =F21-D22+E22 -> -34354.1
B23: Pago METAYER-JEAN | C23: 45342 | E23: 38625 | F23: =F22-D23+E23 -> 4270.9
B24: Cargo MoneyGram/Deposito Banco-Gasto Personal-A2 | C24: 45342 | D24: 1000 | F24: =F23-D24+E24 -> 3270.9
B25: 2do Trimestre 2024 (Abril – Junio) / Gastos común provisional | C25: 45397 | D25: 16428.33 | E25: 3270.9 | F25: =F24-D25+E25 -> -9886.53
B26: 2do Trimestre 2024 (Abril – Junio) / Fondo de Reservas 2024 | C26: 45397 | D26: 1316.2725 | F26: =F25-D26+E26 -> -11202.803
B27: Pedido de fondo – cuota extraordinaria Voto electronico del 09-04-2024 | C27: 45397 | D27: 10282.093 | F27: =F26-D27+E27 -> -21484.895
B28: Pago METAYER-JEAN | C28: 45408 | E28: 22556.56 | F28: =F27-D28+E28 -> 1071.6647
B29: 3er Trimestre 2024 (Julio– Septiembre) / Gastos común provisional | C29: 45474 | D29: ='Presupuesto 2024 Aprobado'!C51 -> 16428.33 | F29: =F28-D29+E29 -> -15356.665
B30: 3er Trimestre 2024 (Julio– Septiembre) / Fondo de Reservas 2024 | C30: 45474 | D30: ='Presupuesto 2024 Aprobado'!D51 -> 1316.2725 | F30: =F29-D30+E30 -> -16672.938
B31: Pago METAYER-JEAN | C31: 45488 | E31: 18000 | F31: =F30-D31+E31 -> 1327.0622
B32: Pedido de fondo – cuota excepcional agosto-2024 | C32: 45510 | D32: 9436.5 | F32: =F31-D32+E32 -> -8109.4378
B33: Rectificación error del 15/04/2024 | C33: 45517 | D33: 3270.9 | F33: =F32-D33+E33 -> -11380.338
B34: Pago METAYER-JEAN | C34: 45531 | E34: 12400 | F34: =F33-D34+E34 -> 1019.6622
B35: 4to Trimestre 2024 (Octubre– Diciembre) / Gastos común provisional | C35: 45566 | D35: ='Presupuesto 2024 Aprobado'!C51 -> 16428.33 | F35: =F34-D35+E35 -> -15408.668
B36: 4to Trimestre 2024 (Octubre– Diciembre) / Fondo de Reservas 2024 | C36: 45566 | D36: ='Presupuesto 2024 Aprobado'!D51 -> 1316.2725 | F36: =F35-D36+E36 -> -16724.94
B37: Pago METAYER-JEAN | C37: 45581 | E37: 18025 | F37: =F36-D37+E37 -> 1300.0597
B38: Pago METAYER-JEAN | C38: 45621 | E38: 10000 | F38: =F37-D38+E38 -> 11300.06
B39: Pedido de fondo – cuota extraordinaria Voto electronico del 11-10-2024 | C39: 45664 | D39: ='PedidoVotoElec-11-10'!E32 -> 6192.901 | F39: =F38-D39+E39 -> 5107.1587
B40: Pedido de fondo – cuota extraordinaria Voto electronico del 09-12-2024 | C40: 45664 | D40: ='PedidoVotoElec-09-12'!E33 -> 14739.636 | F40: =F39-D40+E40 -> -9632.4771
B41: Pedido Excepcional- Enero 2025 | C41: 45664 | D41: ='Pedido Exceptional - ENERO2025'!E26 -> 5553.4394 | F41: =F40-D41+E41 -> -15185.916
C42: TOTAL A2-METAYER | D42: =SUM(D13:D41) -> 253578.38 | E42: =SUM(E13:E41) -> 238392.46 | F42: =E42-D42 -> -15185.916
B44: GASTOS PRIVADO - Aparte de los gastos comunes
B45: Cargo MoneyGram/Deposito Banco | C45: 45408 | D45: -1000 | F45: =F42+D44+D45 -> -16185.916
F46: TOTAL en Crédito
B47: Nota Importante:
B48: Su estado de cuenta está en manera provisional hasta que se cierran las contabilidades del 2024.
B50: Banco POPULAR
B51: Cuenta Corriente - Sra YUNAIRY ENCARNACION - Cedula 134-0005411-3
B52: Cuenta : 0839787280
B53: Pesos

Sheet A3
A3: CONDOMINIO EL FRAMBOYANT
A4: Calle 30 de Marzo, Las Terrenas, Samaná, República Dominicana 32200
B5: Apartamento A3
B6: Frédéric ONDELLA | D6: Fecha limite de pago : 23.01.25
B7: ondellaf@yahoo.fr
G9: Periodo de 01/01/2024 hasta 07/01/2025
B10: Estado de cuenta
B12: Descripción | C12: Fecha | D12: Débito | E12: Crédito | F12: Saldo
B13: Pago Frédéric ONDELLA | C13: 45111 | E13: 7080 | F13: =E13 -> 7080
B14: Pago Frédéric ONDELLA | C14: 45117 | E14: 5900 | F14: =F13-D14+E14 -> 12980
B15: Pago Frédéric ONDELLA | C15: 45219 | E15: 30110 | F15: =F14-D15+E15 -> 43090
B16: Pago Frédéric ONDELLA | C16: 45238 | E16: 88000 | F16: =F15-D16+E16 -> 131090
B17: Pago Frédéric ONDELLA | C17: 45250 | E17: 3530 | F17: =F16-D17+E17 -> 134620
B18: SALDO ANTERIOR | C18: 45291 | F18: =F17-D18+E18 -> 134620
B19: Pedido de fondo – cuota extraordinaria AGE del 12-01-2024 | C19: 45321 | D19: 24132.96 | F19: =F18-D19+E19 -> 110487.04
B20: Pago Frédéric ONDELLA | C20: 45335 | E20: 24134 | F20: =F19-D20+E20 -> 134621.04
B21: Gastos Total año 2023 (Aprobado en AGO del 13 febrero 2024) | C21: 45335 | D21: 125141.93 | F21: =F20-D21+E21 -> 9479.11
B22: Fondo de Reservas 2023 (Pedido del 01/10/2023 - Total $40,000RD) | C22: 45335 | D22: 6195.41 | F22: =F21-D22+E22 -> 3283.7
B23: 1er Trimestre 2024 (Enero – Marzo) / Gastos común provisional | C23: 45336 | D23: 19331.14 | F23: =F22-D23+E23 -> -16047.44
B24: 1er Trimestre 2024 (Enero – Marzo) / Fondo de Reservas 2024 | C24: 45336 | D24: 1548.85 | F24: =F23-D24+E24 -> -17596.29
B25: Pago Frédéric ONDELLA | C25: 45358 | E25: 17600 | F25: =F24-D25+E25 -> 3.71
B26: 2do Trimestre 2024 (Abril – Junio) / Gastos común provisional | C26: 45397 | D26: 19331.143 | F26: =F25-D26+E26 -> -19327.432
B27: 2do Trimestre 2024 (Abril – Junio) / Fondo de Reservas 2024 | C27: 45397 | D27: 1548.8525 | F27: =F26-D27+E27 -> -20876.285
B28: Pedido de fondo – cuota extraordinaria Voto electronico del 09-04-2024 | C28: 45397 | D28: 12098.892 | F28: =F27-D28+E28 -> -32975.177
B29: Pago Frédéric ONDELLA | C29: 45412 | E29: 33000 | F29: =F28-D29+E29 -> 24.823347
B30: 3er Trimestre 2024 (Julio– Septiembre) / Gastos común provisional | C30: 45474 | D30: ='Presupuesto 2024 Aprobado'!C52 -> 19331.143 | F30: =F29-D30+E30 -> -19306.319
B31: 3er Trimestre 2024 (Julio– Septiembre) / Fondo de Reservas 2024 | C31: 45474 | D31: ='Presupuesto 2024 Aprobado'!D52 -> 1548.8525 | F31: =F30-D31+E31 -> -20855.172
B32: Pago Frédéric ONDELLA | C32: 45490 | E32: 20900 | F32: =F31-D32+E32 -> 44.828347
B33: Pedido de fondo – cuota excepcional agosto-2024 | C33: 45510 | D33: 11103.89 | F33: =F32-D33+E33 -> -11059.062
B34: Pago Frédéric ONDELLA | C34: 45534 | E34: 11100 | F34: =F33-D34+E34 -> 40.938347
B35: 4to Trimestre 2024 (Octubre– Diciembre) / Gastos común provisional | C35: 45566 | D35: ='Presupuesto 2024 Aprobado'!C52 -> 19331.143 | F35: =F34-D35+E35 -> -19290.204
B36: 4to Trimestre 2024 (Octubre– Diciembre) / Fondo de Reservas 2024 | C36: 45566 | D36: ='Presupuesto 2024 Aprobado'!D52 -> 1548.8525 | F36: =F35-D36+E36 -> -20839.057
B37: Pago Frédéric ONDELLA | C37: 45570 | E37: 21000 | F37: =F36-D37+E37 -> 160.94335
B38: Pedido de fondo – cuota extraordinaria Voto electronico del 11-10-2024 | C38: 45664 | D38: ='PedidoVotoElec-11-10'!E33 -> 7287.1583 | F38: =F37-D38+E38 -> -7126.215
B39: Pedido de fondo – cuota extraordinaria Voto electronico del 09-12-2024 | C39: 45664 | D39: ='PedidoVotoElec-09-12'!E34 -> 17344.062 | F39: =F38-D39+E39 -> -24470.277
B40: Pedido Excepcional- Enero 2025 | C40: 45664 | D40: ='Pedido Exceptional - ENERO2025'!E27 -> 6534.7067 | F40: =F39-D40+E40 -> -31004.984
C41: TOTAL A3-ONDELLA | D41: =SUM(D13:D40) -> 293358.98 | E41: =SUM(E13:E40) -> 262354 | F41: =E41-D41 -> -31004.984
B43: GASTOS PRIVADO - Aparte de los gastos comunes
B44: COMPRA DE 3 CAMION DE AGUA, fuga de agua flotador tinaco A-3 | C44: 45597 | D44: -3000
B45: COMPRA DE MEDIO CAMION DE AGUA, A-3, averia inapa | C45: 45608 | D45: -500
F46: =F41+D44+D45 -> -34504.984
F47: TOTAL en Debido
B49: Nota Importante:
B50: Su estado de cuenta está en manera provisional hasta que se cierran las contabilidades del 2024.
B52: Banco POPULAR
B53: Cuenta Corriente - Sra YUNAIRY ENCARNACION - Cedula 134-0005411-3
B54: Cuenta : 0839787280
B55: Pesos

Sheet A4
A3: CONDOMINIO EL FRAMBOYANT
A4: Calle 30 de Marzo, Las Terrenas, Samaná, República Dominicana 32200
B5: Apartamento A-4
B6: Patricia FACQUET | D6: Fecha limite de pago : 23.01.25
B7: patriciafacquet@icloud.com
G9: Periodo de 01/01/2024 hasta 07/01/2025
B10: Estado de cuenta
B12: Descripción | C12: Fecha | D12: Débito | E12: Crédito | F12: Saldo
B13: Pago Patricia FACQUET | C13: 45117 | E13: 5900 | F13: =E13 -> 5900
B14: Pago por CH para Patricia FACQUET | C14: 45197 | E14: 3600 | F14: =F13-D14+E14 -> 9500
B15: Pago por CH para Patricia FACQUET | C15: 45229 | E15: 15300 | F15: =F14-D15+E15 -> 24800
B16: Pago por Manon para Patricia FACQUET | C16: 45258 | E16: 46400 | F16: =F15-D16+E16 -> 71200
B17: SALDO ANTERIOR | C17: 45291 | F17: =F16-D17+E17 -> 71200
B18: Pedido de fondo – cuota extraordinaria AGE del 12-01-2024 | C18: 45321 | D18: 12239.9 | F18: =F17-D18+E18 -> 58960.1
B19: Gastos Total año 2023 (Aprobado en AGO del 13 febrero 2024) | C19: 45335 | D19: 63470.2 | F19: =F18-D19+E19 -> -4510.1
B20: Fondo de Reservas 2023 (Pedido del 01/10/2023 - Total $40,000RD) | C20: 45335 | D20: 3142.22 | F20: =F19-D20+E20 -> -7652.32
B21: 1er Trimestre 2024 (Enero – Marzo) / Gastos común provisional | C21: 45336 | D21: 9804.48 | F21: =F20-D21+E21 -> -17456.8
B22: 1er Trimestre 2024 (Enero – Marzo) / Fondo de Reservas 2024 | C22: 45336 | D22: 785.56 | F22: =F21-D22+E22 -> -18242.36
B23: Pago Patricia FACQUET | C23: 45342 | E23: 12230 | F23: =F22-D23+E23 -> -6012.36
B24: Pago Patricia FACQUET | C24: 45359 | E24: 6015 | F24: =F23-D24+E24 -> 2.64
B25: 2do Trimestre 2024 (Abril – Junio) / Gastos común provisional | C25: 45397 | D25: 9804.48 | F25: =F24-D25+E25 -> -9801.84
B26: 2do Trimestre 2024 (Abril – Junio) / Fondo de Reservas 2024 | C26: 45397 | D26: 785.555 | F26: =F25-D26+E26 -> -10587.395
B27: Pedido de fondo – cuota extraordinaria Voto electronico del 09-04-2024 | C27: 45397 | D27: 6163.1818 | F27: =F26-D27+E27 -> -16750.577
B28: Pago Patricia FACQUET | C28: 45415 | E28: 16750.58 | F28: =F27-D28+E28 -> 0.0031610352
B29: 3er Trimestre 2024 (Julio– Septiembre) / Gastos común provisional | C29: 45474 | D29: ='Presupuesto 2024 Aprobado'!C53 -> 9804.48 | F29: =F28-D29+E29 -> -9804.4768
B30: 3er Trimestre 2024 (Julio– Septiembre) / Fondo de Reservas 2024 | C30: 45474 | D30: ='Presupuesto 2024 Aprobado'!D53 -> 785.555 | F30: =F29-D30+E30 -> -10590.032
B31: Pago Patricia FACQUET | C31: 45488 | E31: 10600 | F31: =F30-D31+E31 -> 9.968161
B32: Pedido de fondo – cuota excepcional agosto-2024 | C32: 45510 | D32: 5656.33 | F32: =F31-D32+E32 -> -5646.3618
B33: Pago Patricia FACQUET | C33: 45534 | E33: 5650 | F33: =F32-D33+E33 -> 3.638161
B34: 4to Trimestre 2024 (Octubre– Diciembre) / Gastos común provisional | C34: 45566 | D34: ='Presupuesto 2024 Aprobado'!C53 -> 9804.48 | F34: =F33-D34+E34 -> -9800.8418
B35: 4to Trimestre 2024 (Octubre– Diciembre) / Fondo de Reservas 2024 | C35: 45566 | D35: ='Presupuesto 2024 Aprobado'!D53 -> 785.555 | F35: =F34-D35+E35 -> -10586.397
B36: Pago Patricia FACQUET | C36: 45586 | E36: 10600 | F36: =F35-D36+E36 -> 13.603161
B37: Pedido de fondo – cuota extraordinaria Voto electronico del 11-10-2024 | C37: 45664 | D37: ='PedidoVotoElec-11-10'!E34 -> 3712.0823 | F37: =F36-D37+E37 -> -3698.4792
B38: Pedido de fondo – cuota extraordinaria Voto electronico del 09-12-2024 | C38: 45664 | D38: ='PedidoVotoElec-09-12'!E35 -> 8835.0744 | F38: =F37-D38+E38 -> -12533.554
B39: Pedido Excepcional- Enero 2025 | C39: 45664 | D39: ='Pedido Exceptional - ENERO2025'!E28 -> 3328.7831 | F39: =F38-D39+E39 -> -15862.337
C40: TOTAL A4-FACQUET | D40: =SUM(D13:D39) -> 148907.92 | E40: =SUM(E13:E39) -> 133045.58 | F40: =E40-D40 -> -15862.337
B42: Nota Importante:
B43: Su estado de cuenta está en manera provisional hasta que se cierran las contabilidades del 2024.
B45: Banco POPULAR
B46: Cuenta Corriente - Sra YUNAIRY ENCARNACION - Cedula 134-0005411-3
B47: Cuenta : 0839787280
B48: Pesos

Sheet A5
A3: CONDOMINIO EL FRAMBOYANT
A4: Calle 30 de Marzo, Las Terrenas, Samaná, República Dominicana 32200
B5: Apartamento A-5
B6: Gernot ENGEL | D6: Fecha limite de pago : 23.01.25
B7: gernot.engel2@gmail.com
G9: Periodo de 01/01/2024 hasta 07/01/2025
B10: Estado de cuenta
B12: Descripción | C12: Fecha | D12: Débito | E12: Crédito | F12: Saldo
B13: Pago Gernot ENGEL | C13: 45117 | E13: 5900 | F13: =E13 -> 5900
B14: Pago Gernot ENGEL | C14: 45117 | E14: 4425 | F14: =F13-D14+E14 -> 10325
B15: Pago Gernot ENGEL | C15: 45208 | E15: 18821 | F15: =F14-D15+E15 -> 29146
B16: Pago Gernot ENGEL | C16: 45245 | E16: 57225 | F16: =F15-D16+E16 -> 86371
B17: SALDO ANTERIOR | C17: 45291 | F17: =F16-D17+E17 -> 86371
B18: Pedido de fondo – cuota extraordinaria AGE del 12-01-2024 | C18: 45321 | D18: 15084.59 | F18: =F17-D18+E18 -> 71286.41
B19: Gastos Total año 2023 (Aprobado en AGO del 13 febrero 2024) | C19: 45335 | D19: 78221.4 | F19: =F18-D19+E19 -> -6934.99
B20: Fondo de Reservas 2023 (Pedido del 01/10/2023 - Total $40,000RD) | C20: 45335 | D20: 3872.51 | F20: =F19-D20+E20 -> -10807.5
B21: 1er Trimestre 2024 (Enero – Marzo) / Gastos común provisional | C21: 45336 | D21: 12083.15 | F21: =F20-D21+E21 -> -22890.65
B22: 1er Trimestre 2024 (Enero – Marzo) / Fondo de Reservas 2024 | C22: 45336 | D22: 968.13 | F22: =F21-D22+E22 -> -23858.78
B23: Pago Gernot ENGEL | C23: 45336 | E23: 15000 | F23: =F22-D23+E23 -> -8858.78
B24: Pago Gernot ENGEL | C24: 45358 | E24: 8900 | F24: =F23-D24+E24 -> 41.22
B25: 2do Trimestre 2024 (Abril – Junio) / Gastos común provisional | C25: 45397 | D25: 12083.153 | F25: =F24-D25+E25 -> -12041.932
B26: 2do Trimestre 2024 (Abril – Junio) / Fondo de Reservas 2024 | C26: 45397 | D26: 968.1275 | F26: =F25-D26+E26 -> -13010.06
B27: Pedido de fondo – cuota extraordinaria Voto electronico del 09-04-2024 | C27: 45397 | D27: 7562.5516 | F27: =F26-D27+E27 -> -20572.612
B28: Pago Gernot ENGEL | C28: 45404 | E28: 18600 | F28: =F27-D28+E28 -> -1972.6116
B29: Pago Gernot ENGEL | C29: 45414 | E29: 2000 | F29: =F28-D29+E29 -> 27.388372
B30: 3er Trimestre 2024 (Julio– Septiembre) / Gastos común provisional | C30: 45474 | D30: ='Presupuesto 2024 Aprobado'!C54 -> 12083.153 | F30: =F29-D30+E30 -> -12055.764
B31: 3er Trimestre 2024 (Julio– Septiembre) / Fondo de Reservas 2024 | C31: 45474 | D31: ='Presupuesto 2024 Aprobado'!D54 -> 968.1275 | F31: =F30-D31+E31 -> -13023.892
B32: Pago Gernot ENGEL | C32: 45488 | E32: 13025 | F32: =F31-D32+E32 -> 1.1083715
B33: Pedido de fondo – cuota excepcional agosto-2024 | C33: 45510 | D33: 6940.61 | F33: =F32-D33+E33 -> -6939.5016
B34: Pago Gernot ENGEL | C34: 45527 | E34: 7000 | F34: =F33-D34+E34 -> 60.498372
B35: 4to Trimestre 2024 (Octubre– Diciembre) / Gastos común provisional | C35: 45566 | D35: ='Presupuesto 2024 Aprobado'!C54 -> 12083.153 | F35: =F34-D35+E35 -> -12022.654
B36: 4to Trimestre 2024 (Octubre– Diciembre) / Fondo de Reservas 2024 | C36: 45566 | D36: ='Presupuesto 2024 Aprobado'!D54 -> 968.1275 | F36: =F35-D36+E36 -> -12990.782
B37: Pago Gernot ENGEL | C37: 45576 | E37: 13000 | F37: =F36-D37+E37 -> 9.2183715
B38: Pedido de fondo – cuota extraordinaria Voto electronico del 11-10-2024 | C38: 45664 | D38: ='PedidoVotoElec-11-10'!E35 -> 4554.9223 | F38: =F37-D38+E38 -> -4545.7039
B39: Pedido de fondo – cuota extraordinaria Voto electronico del 09-12-2024 | C39: 45664 | D39: ='PedidoVotoElec-09-12'!E36 -> 10841.106 | F39: =F38-D39+E39 -> -15386.81
B40: Pedido Excepcional- Enero 2025 | C40: 45664 | D40: ='Pedido Exceptional - ENERO2025'!E29 -> 4084.5937 | F40: =F39-D40+E40 -> -19471.403
C41: TOTAL A5-ENGER | D41: =SUM(D13:D40) -> 183367.4 | E41: =SUM(E13:E40) -> 163896 | F41: =E41-D41 -> -19471.403
B43: Nota Importante:
B44: Su estado de cuenta está en manera provisional hasta que se cierran las contabilidades del 2024.
B46: Banco POPULAR
B47: Cuenta Corriente - Sra YUNAIRY ENCARNACION - Cedula 134-0005411-3
B48: Cuenta : 0839787280
B49: Pesos

Sheet A6
A3: CONDOMINIO EL FRAMBOYANT
A4: Calle 30 de Marzo, Las Terrenas, Samaná, República Dominicana 32200
B5: Apartamento A-6
B6: Inversiones Ter 187, eirl / Karina SANTOS | D6: Fecha limite de pago : 23.01.25
B7: skangelical77@gmail.com
G9: Periodo de 01/01/2024 hasta 07/01/2025
B10: Estado de cuenta
B12: Descripción | C12: Fecha | D12: Débito | E12: Crédito | F12: Saldo
B13: Pago Karina SANTOS | C13: 45117 | E13: 5900 | F13: =E13 -> 5900
B14: Pago Karina SANTOS | C14: 45117 | E14: 7272 | F14: =F13-D14+E14 -> 13172
B15: Pago Karina SANTOS | C15: 45217 | E15: 30925 | F15: =F14-D15+E15 -> 44097
B16: Pago Karina SANTOS | C16: 45246 | E16: 94010 | F16: =F15-D16+E16 -> 138107
B17: SALDO ANTERIOR | C17: 45291 | F17: =F16-D17+E17 -> 138107
B18: Pedido de fondo – cuota extraordinaria AGE del 12-01-2024 | C18: 45321 | D18: 24786.23 | F18: =F17-D18+E18 -> 113320.77
B19: Pago Karina SANTOS | C19: 45334 | E19: 24787 | F19: =F18-D19+E19 -> 138107.77
B20: Gastos Total año 2023 (Aprobado en AGO del 13 febrero 2024) | C20: 45335 | D20: 128529.47 | F20: =F19-D20+E20 -> 9578.3
B21: Fondo de Reservas 2023 (Pedido del 01/10/2023 - Total $40,000RD) | C21: 45335 | D21: 6363.12 | F21: =F20-D21+E21 -> 3215.18
B22: 1er Trimestre 2024 (Enero – Marzo) / Gastos común provisional | C22: 45336 | D22: 19854.43 | F22: =F21-D22+E22 -> -16639.25
B23: 1er Trimestre 2024 (Enero – Marzo) / Fondo de Reservas 2024 | C23: 45336 | D23: 1590.78 | F23: =F22-D23+E23 -> -18230.03
B24: Pago Karina SANTOS | C24: 45358 | E24: 18230.03 | F24: =F23-D24+E24 -> 0
B25: 2do Trimestre 2024 (Abril – Junio) / Gastos común provisional | C25: 45397 | D25: 19854.428 | F25: =F24-D25+E25 -> -19854.428
B26: 2do Trimestre 2024 (Abril – Junio) / Fondo de Reservas 2024 | C26: 45397 | D26: 1590.78 | F26: =F25-D26+E26 -> -21445.208
B27: Pedido de fondo – cuota extraordinaria Voto electronico del 09-04-2024 | C27: 45397 | D27: 12426.404 | F27: =F26-D27+E27 -> -33871.611
B28: Pago Karina SANTOS | C28: 45412 | E28: 33871.61 | F28: =F27-D28+E28 -> -0.0012309679
B29: 3er Trimestre 2024 (Julio– Septiembre) / Gastos común provisional | C29: 45474 | D29: ='Presupuesto 2024 Aprobado'!C55 -> 19854.428 | F29: =F28-D29+E29 -> -19854.429
B30: 3er Trimestre 2024 (Julio– Septiembre) / Fondo de Reservas 2024 | C30: 45474 | D30: ='Presupuesto 2024 Aprobado'!D55 -> 1590.78 | F30: =F29-D30+E30 -> -21445.209
B31: Pago Karina SANTOS | C31: 45484 | E31: 21445.21 | F31: =F30-D31+E31 -> 0.0012690321
B32: Pedido de fondo – cuota excepcional agosto-2024 | C32: 45510 | D32: 11404.47 | F32: =F31-D32+E32 -> -11404.469
B33: Pago Karina SANTOS | C33: 45530 | E33: 11404.47 | F33: =F32-D33+E33 -> 0.0012690321
B34: 4to Trimestre 2024 (Octubre– Diciembre) / Gastos común provisional | C34: 45566 | D34: ='Presupuesto 2024 Aprobado'!C55 -> 19854.428 | F34: =F33-D34+E34 -> -19854.426
B35: 4to Trimestre 2024 (Octubre– Diciembre) / Fondo de Reservas 2024 | C35: 45566 | D35: ='Presupuesto 2024 Aprobado'!D55 -> 1590.78 | F35: =F34-D35+E35 -> -21445.206
B36: Pago Karina SANTOS | C36: 45579 | E36: 21455.21 | F36: =F35-D36+E36 -> 10.003769
B37: Pedido de fondo – cuota extraordinaria Voto electronico del 11-10-2024 | C37: 45664 | D37: ='PedidoVotoElec-11-10'!E36 -> 7484.4187 | F37: =F36-D37+E37 -> -7474.415
B38: Pedido de fondo – cuota extraordinaria Voto electronico del 09-12-2024 | C38: 45664 | D38: ='PedidoVotoElec-09-12'!E37 -> 17813.559 | F38: =F37-D38+E38 -> -25287.974
B39: Pedido Excepcional- Enero 2025 | C39: 45664 | D39: ='Pedido Exceptional - ENERO2025'!E30 -> 6711.5986 | F39: =F38-D39+E39 -> -31999.572
C40: TOTAL A6-SANTOS | D40: =SUM(D13:D39) -> 301300.1 | E40: =SUM(E13:E39) -> 269300.53 | F40: =E40-D40 -> -31999.572
B42: Nota Importante:
B43: Su estado de cuenta está en manera provisional hasta que se cierran las contabilidades del 2024.
B45: Banco POPULAR
B46: Cuenta Corriente - Sra YUNAIRY ENCARNACION - Cedula 134-0005411-3
B47: Cuenta : 0839787280
B48: Pesos

Sheet A7
A3: CONDOMINIO EL FRAMBOYANT
A4: Calle 30 de Marzo, Las Terrenas, Samaná, República Dominicana 32200
B5: Apartamento A-7
B6: Jonathan & Stacy HAZELTINE | D6: Fecha limite de pago : 23.01.25
B7: jon@sweetspot.property
G9: Periodo de 01/01/2024 hasta 07/01/2025
B10: Estado de cuenta
B12: Descripción | C12: Fecha | D12: Débito | E12: Crédito | F12: Saldo
B13: Pago HAZELTINE | C13: 45110 | E13: 11424 | F13: =E13 -> 11424
B14: Pago HAZELTINE | C14: 45117 | E14: 5900 | F14: =F13-D14+E14 -> 17324
B15: Pago HAZELTINE | C15: 45203 | E15: 48596 | F15: =F14-D15+E15 -> 65920
B16: Pago HAZELTINE | C16: 45252 | E16: 147723.95 | F16: =F15-D16+E16 -> 213643.95
B17: SALDO ANTERIOR | C17: 45291 | F17: =F16-D17+E17 -> 213643.95
B18: Pedido de fondo – cuota extraordinaria AGE del 12-01-2024 | C18: 45321 | D18: 38949.11 | F18: =F16-D18+E18 -> 174694.84
B19: Gastos Total año 2023 (Aprobado en AGO del 13 febrero 2024) | C19: 45335 | D19: 201971.36 | F19: =F18-D19+E19 -> -27276.52
B20: Fondo de Reservas 2023 (Pedido del 01/10/2023 - Total $40,000RD) | C20: 45335 | D20: 9999.01 | F20: =F19-D20+E20 -> -37275.53
B21: 1er Trimestre 2024 (Enero – Marzo) / Gastos común provisional | C21: 45336 | D21: 31199.27 | F21: =F20-D21+E21 -> -68474.8
B22: 1er Trimestre 2024 (Enero – Marzo) / Fondo de Reservas 2024 | C22: 45336 | D22: 2499.75 | F22: =F21-D22+E22 -> -70974.55
B23: Pago HAZELTINE | C23: 45338 | E23: 44170.7 | F23: =F22-D23+E23 -> -26803.85
B24: Pago HAZELTINE (26,803.85 + 5,221.59) | C24: 45343 | E24: 26803.85 | F24: =F23-D24+E24 -> 3.6379788e-11
B25: 2do Trimestre 2024 (Abril – Junio) / Gastos común provisional | C25: 45397 | D25: 31199.272 | F25: =F24-D25+E25 -> -31199.272
B26: 2do Trimestre 2024 (Abril – Junio) / Fondo de Reservas 2024 | C26: 45397 | D26: 2499.7525 | F26: =F25-D26+E26 -> -33699.025
B27: Pedido de fondo – cuota extraordinaria Voto electronico del 09-04-2024 | C27: 45397 | D27: 19526.866 | F27: =F26-D27+E27 -> -53225.891
B28: Pago HAZELTINE | C28: 45411 | E28: 53225.89 | F28: =F27-D28+E28 -> -0.00059066035
B29: 3er Trimestre 2024 (Julio– Septiembre) / Gastos común provisional | C29: 45474 | D29: ='Presupuesto 2024 Aprobado'!C56 -> 31199.272 | F29: =F28-D29+E29 -> -31199.273
B30: 3er Trimestre 2024 (Julio– Septiembre) / Fondo de Reservas 2024 | C30: 45474 | D30: ='Presupuesto 2024 Aprobado'!D56 -> 2499.7525 | F30: =F29-D30+E30 -> -33699.026
B31: Pago HAZELTINE | C31: 45488 | E31: 33699.03 | F31: =F30-D31+E31 -> 0.0044093397
B32: Pedido de fondo – cuota excepcional agosto-2024 | C32: 45510 | D32: 17921 | F32: =F31-D32+E32 -> -17920.996
B33: Pago HAZELTINE | C33: 45528 | E33: 17921 | F33: =F32-D33+E33 -> 0.0044093397
B34: 4to Trimestre 2024 (Octubre– Diciembre) / Gastos común provisional | C34: 45566 | D34: ='Presupuesto 2024 Aprobado'!C56 -> 31199.272 | F34: =F33-D34+E34 -> -31199.268
B35: 4to Trimestre 2024 (Octubre– Diciembre) / Fondo de Reservas 2024 | C35: 45566 | D35: ='Presupuesto 2024 Aprobado'!D56 -> 2499.7525 | F35: =F34-D35+E35 -> -33699.021
B36: Pago HAZELTINE | C36: 45570 | E36: 33699.02 | F36: =F35-D36+E36 -> -0.00059066035
B37: Pedido de fondo – cuota extraordinaria Voto electronico del 11-10-2024 | C37: 45664 | D37: ='PedidoVotoElec-11-10'!E37 -> 11761.024 | F37: =F36-D37+E37 -> -11761.025
B38: Pedido de fondo – cuota extraordinaria Voto electronico del 09-12-2024 | C38: 45664 | D38: ='PedidoVotoElec-09-12'!E38 -> 27992.247 | F38: =F37-D38+E38 -> -39753.272
B39: Pedido Excepcional- Enero 2025 | C39: 45664 | D39: ='Pedido Exceptional - ENERO2025'!E31 -> 10546.614 | F39: =F38-D39+E39 -> -50299.886
C40: TOTAL A7-HAZELTINE | D40: =SUM(D13:D39) -> 473463.33 | E40: =SUM(E13:E39) -> 423163.44 | F40: =F24-D40+E40 -> -50299.886
B42: GASTOS PRIVADO - Aparte de los gastos comunes
B43: COMPRA DE 1 CAMION DE AGUA, fuga de agua lavamano segundo piso | C43: 45614 | D43: -1000
B44: COMPRA DE 1 CAMION DE AGUA, fuga de agua | C44: 45645 | D44: -1000
B45: COMPRA DE 1 CAMION DE AGUA, fuga de agua | C45: 45647 | D45: -1000
F46: =F40+D43+D4+D44+D45 -> -53299.886
B47: Nota Importante: | G47: TOTAL en Debido
B48: Su estado de cuenta está en manera provisional hasta que se cierran las contabilidades del 2024.
B50: Banco POPULAR
B51: Cuenta Corriente - Sra YUNAIRY ENCARNACION - Cedula 134-0005411-3
B52: Cuenta : 0839787280
B53: Pesos

Sheet Distribución
K1: 26236200
B2: Propietario | C2: Unidad | E2: Superficie | F2: Porcentaje | J2: Unidad | K2: Valor RD$ | L2: Repartición % | M2: Repartición % | N2: Repartición
B3: Serge GUERRIN | C3: A-1 | J3: 1 | K3: =K1/J20*J13 -> 3385038.8 | L3: 12.9 | M3: 12.9 | N3: =M3*10000 -> 129000
C4: Apartamento | D4: SP-01-01-001 | E4: 79.09 | J4: 2 | K4: =K1/J20*J14 -> 3452215.8 | L4: 13.16 | M4: 13.16 | N4: =M4*10000 -> 131600
C5: Terraza | D5: SE-01-01-001 | E5: 18.91 | J5: 3 | K5: =K1/J20*J15 -> 4062206.5 | L5: 15.48 | M5: 15.48 | N5: =M5*10000 -> 154800
C6: Jardín | D6: SE-01-01-002 | E6: 71.31 | J6: 4 | K6: =K1/J20*J16 -> 2069290.2 | L6: 7.89 | M6: 7.89 | N6: =M6*10000 -> 78900
E7: =SUM(E4:E6) -> 169.31 | F7: =E7/E44 -> 0.12902169 | G7: 0.129 | J7: 5 | K7: =K1/J20*J17 -> 2539129 | L7: 9.68 | M7: 9.68 | N7: =M7*10000 -> 96800
B8: Herve METAYER | C8: A-2 | J8: 6 | K8: =K1/J20*J18 -> 4172168.8 | L8: 15.9 | M8: 15.9 | N8: =M8*10000 -> 159000
C9: Apartamento | D9: SP-01-01-002 | E9: 90.48 | J9: 7 | K9: =K1/J20*J19 -> 6556151 | L9: 24.99 | M9: 24.99 | N9: =M9*10000 -> 249900
C10: Terraza | D10: SE-01-01-003 | E10: 24.52 | K10: =SUM(K3:K9) -> 26236200 | L10: =SUM(L3:L9) -> 100 | M10: =SUM(M3:M9) -> 100 | N10: =SUM(N3:N9) -> 1000000
C11: Jardín | D11: SE-01-01-004 | E11: 57.67
E12: =SUM(E9:E11) -> 172.67 | F12: =E12/E44 -> 0.13158216 | G12: 0.1316 | I12: Unidad | J12: M2 | K12: Total Unidad | L12: Votos | M12: Votos | N12: Votos
B13: Frédéric ONDELLA | C13: A-3 | I13: 1 | J13: 169.31 | K13: 1 | L13: 0.9031 | M13: 0.9031 | N13: =M13*10000 -> 9031
C14: Apartamento | D14: SP-01-01-003 | E14: 82.55 | I14: 2 | J14: 172.67 | K14: 1 | L14: 0.9211 | M14: 0.9211 | N14: =M14*10000 -> 9211
C15: Terraza | D15: SE-01-01-005 | E15: 25.38 | I15: 3 | J15: 203.18 | K15: 1 | L15: 1.0838 | M15: 1.0838 | N15: =M15*10000 -> 10838
C16: Terraza | D16: SE-01-01-006 | E16: 4.57 | I16: 4 | J16: 103.5 | K16: 1 | L16: 0.5521 | M16: 0.5521 | N16: =M16*10000 -> 5521
C17: Jardín | D17: SE-01-01-007 | E17: 90.68 | I17: 5 | J17: 127 | K17: 1 | L17: 0.6775 | M17: 0.6775 | N17: =M17*10000 -> 6775
E18: =SUM(E14:E17) -> 203.18 | F18: =E18/E44 -> 0.15483212 | G18: 0.1548 | I18: 6 | J18: 208.68 | K18: 1 | L18: 1.1132 | M18: 1.1132 | N18: =M18*10000 -> 11132
B19: Patricia FACQUET | C19: A-4 | I19: 7 | J19: 327.92 | K19: 1 | L19: 1.7492 | M19: 1.7492 | N19: =M19*10000 -> 17492
C20: Apartamento | D20: SP-01-02-001 | E20: 72.59 | J20: =J13+J14+J15+J16+J17+J18+J19 -> 1312.26 | K20: =SUM(K13:K19) -> 7 | L20: =SUM(L13:L19) -> 7 | M20: =SUM(M13:M19) -> 7 | N20: =SUM(N13:N19) -> 70000
C21: Terraza | D21: SE-01-02-001 | E21: 18.91
C22: Parqueo | D22: SE-00-01-002 | E22: 12
E23: =SUM(E20:E22) -> 103.5 | F23: =E23/E44 -> 0.078871565 | G23: 0.0789 | I23: 1 | J23: 169.31 | K23: 1312.26 | L23: 0.129021 | M23: 7 | N23: =L23*M23 -> 0.903147
B24: Gernot ENGER | C24: A-5 | I24: 2 | J24: 172.67 | K24: 1312.26 | L24: 0.131582 | M24: 7 | N24: =L24*M24 -> 0.921074
C25: Apartamento | D25: SP-01-02-002 | E25: 90.48 | I25: 3 | J25: 203.18 | K25: 1312.26 | L25: =J25/K25 -> 0.15483212 | M25: 7 | N25: =L25*M25 -> 1.0838249
C26: Terraza | D26: SE-01-02-002 | E26: 24.52 | I26: 4 | J26: 103.5 | K26: 1312.26 | L26: =J26/K26 -> 0.078871565 | M26: 7 | N26: =L26*M26 -> 0.55210096
C27: Parqueo | D27: SE-00-01-003 | E27: 12 | I27: 5 | J27: 127 | K27: 1312.26 | L27: =J27/K27 -> 0.096779602 | M27: 7 | N27: =L27*M27 -> 0.67745721
E28: =SUM(E25:E27) -> 127 | F28: =E28/E44 -> 0.096779602 | G28: 0.0968 | I28: 6 | J28: 208.68 | K28: 1312.26 | L28: =J28/K28 -> 0.15902336 | M28: 7 | N28: =L28*M28 -> 1.1131635
B29: Inversiones Ter 187 eirl (Karina SANTOS) | C29: A-6 | I29: 7 | J29: 327.92 | K29: 1312.26 | L29: =J29/K29 -> 0.2498895 | M29: 7 | N29: =L29*M29 -> 1.7492265
C30: Apartamento | D30: SP-01-02-003 | E30: 82.55 | J30: =SUM(J23:J29) -> 1312.26 | L30: =SUM(L23:L29) -> 0.99999916 | N30: =SUM(N23:N29) -> 6.9999941
C31: Terraza | D31: SE-01-02-003 | E31: 25.38
C32: Terraza | D32: SE-01-02-004 | E32: 4.57
C33: Parqueo | D33: SE-00-01-004 | E33: 12
C34: Jardín | D34: SE-01-01-008 | E34: 72.46
C35: Escalera | D35: SE-01-01-009 | E35: 6.37
C36: Escalera | D36: SE-01-02-005 | E36: 5.35
E37: =SUM(E30:E36) -> 208.68 | F37: =E37/E44 -> 0.15902336 | G37: 0.159
B38: Jonathan HAZELTINE | C38: A-7
C39: Apartamento | D39: SP-01-03-001 | E39: 123.26
C40: Terraza | D40: SE-01-03-001 | E40: 176.74
C41: Parqueo | D41: SE-00-01-001 | E41: 27.92
E42: =SUM(E39:E41) -> 327.92 | F42: =E42/E44 -> 0.2498895 | G42: 0.2499
D44: TOTAL METRO CUADRADOS | E44: =E7+E12+E18+E23+E28+E37+E42 -> 1312.26 | F44: =SUM(F7:F42) -> 1 | G44: =SUM(G7:G42) -> 1
